{"data":{"INFO":{"CODGRUPO":"44766583","GOLES_CASA":"1","GOLES_FUERA":"0","PENALTIS_CASA":null,"PENALTIS_FUERA":null,"CODACTA":"3009472","COD_COMPETICION":43980440,"NOM_COMPETICION":"CADET PRIMERA DIVISIÓ","NOM_COMPETICION_URL":"cadet-primera-divisio","COD_GRUPO":44766583,"GRUPO":"GRUP 1","GRUPO_URL":"grup-1","CODEQUIPO_CASA":"34584","CODEQUIPO_FUERA":"35623","JORNADA":"19","CODIGO_CAMPO":"520","COMIENZO1":"2023-03-04 17:00:00","SUSPENDIDO":"0","NOMBRE":"CAMP DE FUTBOL MPAL. NOU SARDENYA","DIRECCION":"c/ de les Camèlies, 42B","TEMP_NOMBRE":"2223","TEMP_LARGO":"TEMPORADA 2022-2023","CIUDAD":"Barcelona","ESTADO":"4"},"ARBITROS":[{"CODTIPO_ARBITRO":"1","CODARBITRO":"6628","NOMBRE_ARBITRO":"FRANCESC XAVIER","NOMBRE":"Barcelona1"}],"GOLES":[{"NOMBRE":"MARCO","LICENCIA":"18","DORSAL":"7","CODPARTICIPANTE":"26844460","FECHA_NACIMIENTO":2,"PORTERO":null,"TIPO":"normal","MINUTO":"17","EQUIPO":"local"}],"EQUIPO_CASA":{"CODCLUB":1011,"CODCLUB2":1011,"CODEQUIPO":34584,"NOMBRE_CLUB":"EUROPA, C.E.","NOMBRE_CLUB_URL":"europa-ce","NOMBRE_EQUIPO":"EUROPA, C.E. B","NOMBRE_EQUIPO_URL":"europa-ce-b","NOMBRE":"00100_0000735880_europa_200x200.png","NOMBRE_ABREVIADO_URL":"1c","CODGRUPO":41325884,"TITULARES":[{"NOMBRE":"PAU","LICENCIA":"18","DORSAL":"2","CODPARTICIPANTE":"20111858","FECHA_NACIMIENTO":2,"PORTERO":null},{"NOMBRE":"LUCAS","LICENCIA":"18","DORSAL":"4","CODPARTICIPANTE":"20038706","FECHA_NACIMIENTO":2,"PORTERO":null},{"NOMBRE":"ADRIAN","LICENCIA":"18","DORSAL":"6","CODPARTICIPANTE":"25870636","FECHA_NACIMIENTO":2,"PORTERO":null},{"NOMBRE":"MARCO","LICENCIA":"18","DORSAL":"7","CODPARTICIPANTE":"26844460","FECHA_NACIMIENTO":2,"PORTERO":null},{"NOMBRE":"HECTOR","LICENCIA":"18","DORSAL":"9","CODPARTICIPANTE":"27311422","FECHA_NACIMIENTO":2,"PORTERO":null},{"NOMBRE":"UNAI","LICENCIA":"18","DORSAL":"10","CODPARTICIPANTE":"20112205","FECHA_NACIMIENTO":2,"PORTERO":null},{"NOMBRE":"MARTI","LICENCIA":"18","DORSAL":"13","CODPARTICIPANTE":"22766857","FECHA_NACIMIENTO":2,"PORTERO":1},{"NOMBRE":"SNEIJDER","LICENCIA":"18","DORSAL":"16","CODPARTICIPANTE":"37389386","FECHA_NACIMIENTO":2,"PORTERO":null},{"NOMBRE":"ADRIAN","LICENCIA":"18","DORSAL":"17","CODPARTICIPANTE":"20246071","FECHA_NACIMIENTO":2,"PORTERO":null},{"NOMBRE":"OT","LICENCIA":"18","DORSAL":"18","CODPARTICIPANTE":"31974523","FECHA_NACIMIENTO":2,"PORTERO":null},{"NOMBRE":"EDUARDO","LICENCIA":"18","DORSAL":"21","CODPARTICIPANTE":"26714286","FECHA_NACIMIENTO":2,"PORTERO":null}],"SUPLENTES":[{"NOMBRE":"ALBERT","LICENCIA":"18","DORSAL":"1","CODPARTICIPANTE":"29649258","FECHA_NACIMIENTO":2,"PORTERO":1},{"NOMBRE":"GERARD","LICENCIA":"18","DORSAL":"3","CODPARTICIPANTE":"23648178","FECHA_NACIMIENTO":2,"PORTERO":null},{"NOMBRE":"BIEL","LICENCIA":"18","DORSAL":"8","CODPARTICIPANTE":"23648277","FECHA_NACIMIENTO":2,"PORTERO":null},{"NOMBRE":"AMANUEL PAU","LICENCIA":"18","DORSAL":"14","CODPARTICIPANTE":"37946110","FECHA_NACIMIENTO":2,"PORTERO":null},{"NOMBRE":"THIAGO","LICENCIA":"18","DORSAL":"15","CODPARTICIPANTE":"19686903","FECHA_NACIMIENTO":2,"PORTERO":null},{"NOMBRE":"MARTIN","LICENCIA":"18","DORSAL":"20","CODPARTICIPANTE":"29321013","FECHA_NACIMIENTO":2,"PORTERO":null},{"NOMBRE":"JAN","LICENCIA":"18","DORSAL":"23","CODPARTICIPANTE":"19649150","FECHA_NACIMIENTO":2,"PORTERO":null}],"COSTECNIC":{"Delegat":"TOMÀS","Entrenador Titular":"NIL","Auxiliar":"ALEX"},"SUSTITUCIONES":[],"SANCIONES":[{"NOMBRE":"NIL","LICENCIA":"40492317","DORSAL":"0","CODPARTICIPANTE":"39513579","FECHA_NACIMIENTO":2,"PORTERO":null,"TIPO":"groga","MINUTO":"48"},{"NOMBRE":"LUCAS","LICENCIA":"18","DORSAL":"4","CODPARTICIPANTE":"20038706","FECHA_NACIMIENTO":2,"PORTERO":null,"TIPO":"groga","MINUTO":"36"},{"NOMBRE":"BIEL","LICENCIA":"18","DORSAL":"8","CODPARTICIPANTE":"23648277","FECHA_NACIMIENTO":2,"PORTERO":null,"TIPO":"groga","MINUTO":"67"},{"NOMBRE":"MARTIN","LICENCIA":"18","DORSAL":"20","CODPARTICIPANTE":"29321013","FECHA_NACIMIENTO":2,"PORTERO":null,"TIPO":"groga","MINUTO":"79"}]},"EQUIPO_FUERA":{"CODCLUB":2835,"CODCLUB2":2835,"CODEQUIPO":35623,"NOMBRE_CLUB":"SANT IGNASI C.E.","NOMBRE_CLUB_URL":"sant-ignasi-ce","NOMBRE_EQUIPO":"SANT IGNASI C.E. A","NOMBRE_EQUIPO_URL":"sant-ignasi-ce-a","NOMBRE":"00100_0000664682_stignasice_200x200.png","NOMBRE_ABREVIADO_URL":"1c","CODGRUPO":41325917,"TITULARES":[{"NOMBRE":"JOAN","LICENCIA":"18","DORSAL":"5","CODPARTICIPANTE":"35299373","FECHA_NACIMIENTO":1,"PORTERO":null},{"NOMBRE":"TOMAS","LICENCIA":"18","DORSAL":"8","CODPARTICIPANTE":"32876030","FECHA_NACIMIENTO":1,"PORTERO":null},{"NOMBRE":"PABLO","LICENCIA":"18","DORSAL":"10","CODPARTICIPANTE":"36154064","FECHA_NACIMIENTO":1,"PORTERO":null},{"NOMBRE":"PABLO","LICENCIA":"18","DORSAL":"11","CODPARTICIPANTE":"35374582","FECHA_NACIMIENTO":1,"PORTERO":null},{"NOMBRE":"ALEJANDRO","LICENCIA":"18","DORSAL":"14","CODPARTICIPANTE":"20238098","FECHA_NACIMIENTO":2,"PORTERO":null},{"NOMBRE":"XAVIER","LICENCIA":"18","DORSAL":"19","CODPARTICIPANTE":"33507536","FECHA_NACIMIENTO":1,"PORTERO":null},{"NOMBRE":"GUILLERMO","LICENCIA":"18","DORSAL":"22","CODPARTICIPANTE":"35302687","FECHA_NACIMIENTO":1,"PORTERO":null},{"NOMBRE":"LUCAS","LICENCIA":"18","DORSAL":"34","CODPARTICIPANTE":"35255370","FECHA_NACIMIENTO":2,"PORTERO":null},{"NOMBRE":"BRUNO","LICENCIA":"18","DORSAL":"46","CODPARTICIPANTE":"35299050","FECHA_NACIMIENTO":1,"PORTERO":null},{"NOMBRE":"ALEX","LICENCIA":"18","DORSAL":"69","CODPARTICIPANTE":"27489829","FECHA_NACIMIENTO":1,"PORTERO":null},{"NOMBRE":"JON","LICENCIA":"18","DORSAL":"99","CODPARTICIPANTE":"35298300","FECHA_NACIMIENTO":2,"PORTERO":1}],"SUPLENTES":[{"NOMBRE":"XAVI","LICENCIA":"18","DORSAL":"1","CODPARTICIPANTE":"35303300","FECHA_NACIMIENTO":2,"PORTERO":1},{"NOMBRE":"EDUARDO","LICENCIA":"18","DORSAL":"6","CODPARTICIPANTE":"33035631","FECHA_NACIMIENTO":1,"PORTERO":null},{"NOMBRE":"TYMUR","LICENCIA":"18","DORSAL":"9","CODPARTICIPANTE":"33515893","FECHA_NACIMIENTO":1,"PORTERO":null},{"NOMBRE":"FERNANDO","LICENCIA":"18","DORSAL":"15","CODPARTICIPANTE":"35297870","FECHA_NACIMIENTO":2,"PORTERO":null},{"NOMBRE":"PEP","LICENCIA":"18","DORSAL":"20","CODPARTICIPANTE":"36481330","FECHA_NACIMIENTO":1,"PORTERO":null},{"NOMBRE":"JOSÉ","LICENCIA":"18","DORSAL":"23","CODPARTICIPANTE":"22763192","FECHA_NACIMIENTO":2,"PORTERO":null},{"NOMBRE":"ALBERT","LICENCIA":"18","DORSAL":"50","CODPARTICIPANTE":"23381432","FECHA_NACIMIENTO":2,"PORTERO":null}],"COSTECNIC":{"Auxiliar":"ALEX","Entrenador Titular":"SERGI"},"SUSTITUCIONES":[],"SANCIONES":[{"NOMBRE":"ALEX","LICENCIA":"15","DORSAL":"0","CODPARTICIPANTE":"45375134","FECHA_NACIMIENTO":null,"PORTERO":null,"TIPO":"groga","MINUTO":"60"},{"NOMBRE":"EDUARDO","LICENCIA":"18","DORSAL":"6","CODPARTICIPANTE":"33035631","FECHA_NACIMIENTO":1,"PORTERO":null,"TIPO":"groga","MINUTO":"69"},{"NOMBRE":"BRUNO","LICENCIA":"18","DORSAL":"46","CODPARTICIPANTE":"35299050","FECHA_NACIMIENTO":1,"PORTERO":null,"TIPO":"vermella","MINUTO":"66"}]}},"codacta":"3009472","titulars_local":[{"codparticipant":29649258,"codequip":34584,"dorsal":1,"titularitats":0,"porter":1,"nom":"ALBERT","any":2008,"partits":1,"nom_equip":"EUROPA, C.E. B","colorequipacio1":"#FFFFFF","colorequipacio2":"#FFFF00"},{"codparticipant":20111858,"codequip":34584,"dorsal":2,"titularitats":1,"porter":null,"nom":"PAU","any":2008,"partits":1,"nom_equip":"EUROPA, C.E. B","colorequipacio1":"#FFFFFF","colorequipacio2":"#FFFF00"},{"codparticipant":23648178,"codequip":34584,"dorsal":3,"titularitats":0,"porter":null,"nom":"GERARD","any":2008,"partits":1,"nom_equip":"EUROPA, C.E. B","colorequipacio1":"#FFFFFF","colorequipacio2":"#FFFF00"},{"codparticipant":20038706,"codequip":34584,"dorsal":4,"titularitats":1,"porter":null,"nom":"LUCAS","any":2008,"partits":1,"nom_equip":"EUROPA, C.E. B","colorequipacio1":"#FFFFFF","colorequipacio2":"#FFFF00"},{"codparticipant":25870636,"codequip":34584,"dorsal":6,"titularitats":1,"porter":null,"nom":"ADRIAN","any":2008,"partits":1,"nom_equip":"EUROPA, C.E. B","colorequipacio1":"#FFFFFF","colorequipacio2":"#FFFF00"},{"codparticipant":26844460,"codequip":34584,"dorsal":7,"titularitats":1,"porter":null,"nom":"MARCO","any":2008,"partits":1,"nom_equip":"EUROPA, C.E. B","colorequipacio1":"#FFFFFF","colorequipacio2":"#FFFF00"},{"codparticipant":23648277,"codequip":34584,"dorsal":8,"titularitats":0,"porter":null,"nom":"BIEL","any":2008,"partits":1,"nom_equip":"EUROPA, C.E. B","colorequipacio1":"#FFFFFF","colorequipacio2":"#FFFF00"},{"codparticipant":27311422,"codequip":34584,"dorsal":9,"titularitats":1,"porter":null,"nom":"HECTOR","any":2008,"partits":1,"nom_equip":"EUROPA, C.E. B","colorequipacio1":"#FFFFFF","colorequipacio2":"#FFFF00"},{"codparticipant":20112205,"codequip":34584,"dorsal":10,"titularitats":1,"porter":null,"nom":"UNAI","any":2008,"partits":1,"nom_equip":"EUROPA, C.E. B","colorequipacio1":"#FFFFFF","colorequipacio2":"#FFFF00"},{"codparticipant":22766857,"codequip":34584,"dorsal":13,"titularitats":1,"porter":1,"nom":"MARTI","any":2008,"partits":1,"nom_equip":"EUROPA, C.E. B","colorequipacio1":"#FFFFFF","colorequipacio2":"#FFFF00"},{"codparticipant":37946110,"codequip":34584,"dorsal":14,"titularitats":0,"porter":null,"nom":"AMANUEL PAU","any":2008,"partits":1,"nom_equip":"EUROPA, C.E. B","colorequipacio1":"#FFFFFF","colorequipacio2":"#FFFF00"},{"codparticipant":19686903,"codequip":34584,"dorsal":15,"titularitats":0,"porter":null,"nom":"THIAGO","any":2008,"partits":1,"nom_equip":"EUROPA, C.E. B","colorequipacio1":"#FFFFFF","colorequipacio2":"#FFFF00"},{"codparticipant":37389386,"codequip":34584,"dorsal":16,"titularitats":1,"porter":null,"nom":"SNEIJDER","any":2008,"partits":1,"nom_equip":"EUROPA, C.E. B","colorequipacio1":"#FFFFFF","colorequipacio2":"#FFFF00"},{"codparticipant":20246071,"codequip":34584,"dorsal":17,"titularitats":1,"porter":null,"nom":"ADRIAN","any":2008,"partits":1,"nom_equip":"EUROPA, C.E. B","colorequipacio1":"#FFFFFF","colorequipacio2":"#FFFF00"},{"codparticipant":31974523,"codequip":34584,"dorsal":18,"titularitats":1,"porter":null,"nom":"OT","any":2008,"partits":1,"nom_equip":"EUROPA, C.E. B","colorequipacio1":"#FFFFFF","colorequipacio2":"#FFFF00"},{"codparticipant":29321013,"codequip":34584,"dorsal":20,"titularitats":0,"porter":null,"nom":"MARTIN","any":2008,"partits":1,"nom_equip":"EUROPA, C.E. B","colorequipacio1":"#FFFFFF","colorequipacio2":"#FFFF00"},{"codparticipant":26714286,"codequip":34584,"dorsal":21,"titularitats":1,"porter":null,"nom":"EDUARDO","any":2008,"partits":1,"nom_equip":"EUROPA, C.E. B","colorequipacio1":"#FFFFFF","colorequipacio2":"#FFFF00"},{"codparticipant":19649150,"codequip":34584,"dorsal":23,"titularitats":0,"porter":null,"nom":"JAN","any":2008,"partits":1,"nom_equip":"EUROPA, C.E. B","colorequipacio1":"#FFFFFF","colorequipacio2":"#FFFF00"}],"titulars_visitant":[{"codparticipant":35303300,"codequip":35623,"dorsal":1,"titularitats":0,"porter":1,"nom":"XAVI","any":2008,"partits":1,"nom_equip":"SANT IGNASI C.E. A","colorequipacio1":"#FF0000","colorequipacio2":"#B8B8B8"},{"codparticipant":35299373,"codequip":35623,"dorsal":5,"titularitats":1,"porter":null,"nom":"JOAN","any":2007,"partits":1,"nom_equip":"SANT IGNASI C.E. A","colorequipacio1":"#FF0000","colorequipacio2":"#B8B8B8"},{"codparticipant":33035631,"codequip":35623,"dorsal":6,"titularitats":0,"porter":null,"nom":"EDUARDO","any":2007,"partits":1,"nom_equip":"SANT IGNASI C.E. A","colorequipacio1":"#FF0000","colorequipacio2":"#B8B8B8"},{"codparticipant":32876030,"codequip":35623,"dorsal":8,"titularitats":1,"porter":null,"nom":"TOMAS","any":2007,"partits":1,"nom_equip":"SANT IGNASI C.E. A","colorequipacio1":"#FF0000","colorequipacio2":"#B8B8B8"},{"codparticipant":33515893,"codequip":35623,"dorsal":9,"titularitats":0,"porter":null,"nom":"TYMUR","any":2007,"partits":1,"nom_equip":"SANT IGNASI C.E. A","colorequipacio1":"#FF0000","colorequipacio2":"#B8B8B8"},{"codparticipant":36154064,"codequip":35623,"dorsal":10,"titularitats":1,"porter":null,"nom":"PABLO","any":2007,"partits":1,"nom_equip":"SANT IGNASI C.E. A","colorequipacio1":"#FF0000","colorequipacio2":"#B8B8B8"},{"codparticipant":35374582,"codequip":35623,"dorsal":11,"titularitats":1,"porter":null,"nom":"PABLO","any":2007,"partits":1,"nom_equip":"SANT IGNASI C.E. A","colorequipacio1":"#FF0000","colorequipacio2":"#B8B8B8"},{"codparticipant":20238098,"codequip":35623,"dorsal":14,"titularitats":1,"porter":null,"nom":"ALEJANDRO","any":2008,"partits":1,"nom_equip":"SANT IGNASI C.E. A","colorequipacio1":"#FF0000","colorequipacio2":"#B8B8B8"},{"codparticipant":35297870,"codequip":35623,"dorsal":15,"titularitats":0,"porter":null,"nom":"FERNANDO","any":2008,"partits":1,"nom_equip":"SANT IGNASI C.E. A","colorequipacio1":"#FF0000","colorequipacio2":"#B8B8B8"},{"codparticipant":33507536,"codequip":35623,"dorsal":19,"titularitats":1,"porter":null,"nom":"XAVIER","any":2007,"partits":1,"nom_equip":"SANT IGNASI C.E. A","colorequipacio1":"#FF0000","colorequipacio2":"#B8B8B8"},{"codparticipant":36481330,"codequip":35623,"dorsal":20,"titularitats":0,"porter":null,"nom":"PEP","any":2007,"partits":1,"nom_equip":"SANT IGNASI C.E. A","colorequipacio1":"#FF0000","colorequipacio2":"#B8B8B8"},{"codparticipant":35302687,"codequip":35623,"dorsal":22,"titularitats":1,"porter":null,"nom":"GUILLERMO","any":2007,"partits":1,"nom_equip":"SANT IGNASI C.E. A","colorequipacio1":"#FF0000","colorequipacio2":"#B8B8B8"},{"codparticipant":22763192,"codequip":35623,"dorsal":23,"titularitats":0,"porter":null,"nom":"JOSÉ","any":2008,"partits":1,"nom_equip":"SANT IGNASI C.E. A","colorequipacio1":"#FF0000","colorequipacio2":"#B8B8B8"},{"codparticipant":35255370,"codequip":35623,"dorsal":34,"titularitats":1,"porter":null,"nom":"LUCAS","any":2008,"partits":1,"nom_equip":"SANT IGNASI C.E. A","colorequipacio1":"#FF0000","colorequipacio2":"#B8B8B8"},{"codparticipant":35299050,"codequip":35623,"dorsal":46,"titularitats":1,"porter":null,"nom":"BRUNO","any":2007,"partits":1,"nom_equip":"SANT IGNASI C.E. A","colorequipacio1":"#FF0000","colorequipacio2":"#B8B8B8"},{"codparticipant":23381432,"codequip":35623,"dorsal":50,"titularitats":0,"porter":null,"nom":"ALBERT","any":2008,"partits":1,"nom_equip":"SANT IGNASI C.E. A","colorequipacio1":"#FF0000","colorequipacio2":"#B8B8B8"},{"codparticipant":27489829,"codequip":35623,"dorsal":69,"titularitats":1,"porter":null,"nom":"ALEX","any":2007,"partits":1,"nom_equip":"SANT IGNASI C.E. A","colorequipacio1":"#FF0000","colorequipacio2":"#B8B8B8"},{"codparticipant":35298300,"codequip":35623,"dorsal":99,"titularitats":1,"porter":1,"nom":"JON","any":2008,"partits":1,"nom_equip":"SANT IGNASI C.E. A","colorequipacio1":"#FF0000","colorequipacio2":"#B8B8B8"}],"menuFollowTeams":[{"label":"Cadet A","href":"/classificacio?id=44766647"},{"label":"Cadet B","href":"/classificacio?id=44766583"},{"label":"Cadet C","href":"/classificacio?id=45060588"},{"label":"Cadet D","href":"/classificacio?id=45061869"}]}