{"data":{"INFO":{"CODGRUPO":"44766647","GOLES_CASA":"4","GOLES_FUERA":"1","PENALTIS_CASA":null,"PENALTIS_FUERA":null,"CODACTA":"3009681","COD_COMPETICION":43980440,"NOM_COMPETICION":"CADET PRIMERA DIVISIÓ","NOM_COMPETICION_URL":"cadet-primera-divisio","COD_GRUPO":44766647,"GRUPO":"GRUP 2","GRUPO_URL":"grup-2","CODEQUIPO_CASA":"36242","CODEQUIPO_FUERA":"36122","JORNADA":"15","CODIGO_CAMPO":"262","COMIENZO1":"2023-01-28 16:25:00","SUSPENDIDO":"0","NOMBRE":"CAMP DE FUTBOL CEM CAN CARALLEU","DIRECCION":"c/ dels Esports, 3","TEMP_NOMBRE":"2223","TEMP_LARGO":"TEMPORADA 2022-2023","CIUDAD":"Barcelona","ESTADO":"4"},"ARBITROS":[{"CODTIPO_ARBITRO":"1","CODARBITRO":"8745","NOMBRE_ARBITRO":"ARLEY YAMID","NOMBRE":"Barcelona1"}],"GOLES":[{"NOMBRE":"DAVID","LICENCIA":"18","DORSAL":"5","CODPARTICIPANTE":"28485589","FECHA_NACIMIENTO":1,"PORTERO":null,"TIPO":"normal","MINUTO":"3","EQUIPO":"local"},{"NOMBRE":"JOAN","LICENCIA":"18","DORSAL":"6","CODPARTICIPANTE":"18594366","FECHA_NACIMIENTO":1,"PORTERO":null,"TIPO":"normal","MINUTO":"17","EQUIPO":"local"},{"NOMBRE":"LUCAS","LICENCIA":"18","DORSAL":"9","CODPARTICIPANTE":"26535226","FECHA_NACIMIENTO":1,"PORTERO":null,"TIPO":"normal","MINUTO":"54","EQUIPO":"local"},{"NOMBRE":"ANTONI","LICENCIA":"18","DORSAL":"16","CODPARTICIPANTE":"31668934","FECHA_NACIMIENTO":1,"PORTERO":null,"TIPO":"normal","MINUTO":"72","EQUIPO":"local"},{"NOMBRE":"LUCAS","LICENCIA":"18","DORSAL":"20","CODPARTICIPANTE":"29978742","FECHA_NACIMIENTO":1,"PORTERO":null,"TIPO":"penalti","MINUTO":"33","EQUIPO":"visitante"}],"EQUIPO_CASA":{"CODCLUB":1194,"CODCLUB2":1194,"CODEQUIPO":36242,"NOMBRE_CLUB":"SARRIA, C.P.","NOMBRE_CLUB_URL":"sarria-cp","NOMBRE_EQUIPO":"SARRIA, C.P. A","NOMBRE_EQUIPO_URL":"sarria-cp-a","NOMBRE":"00100_0000388904_00100_0000337753_escut-cp-sarria-1952.png","NOMBRE_ABREVIADO_URL":"1c","CODGRUPO":40987548,"TITULARES":[{"NOMBRE":"AMMAR","LICENCIA":"18","DORSAL":"1","CODPARTICIPANTE":"42741389","FECHA_NACIMIENTO":1,"PORTERO":1},{"NOMBRE":"JORDI","LICENCIA":"18","DORSAL":"3","CODPARTICIPANTE":"23553361","FECHA_NACIMIENTO":1,"PORTERO":null},{"NOMBRE":"DAVID","LICENCIA":"18","DORSAL":"5","CODPARTICIPANTE":"28485589","FECHA_NACIMIENTO":1,"PORTERO":null},{"NOMBRE":"JOAN","LICENCIA":"18","DORSAL":"6","CODPARTICIPANTE":"18594366","FECHA_NACIMIENTO":1,"PORTERO":null},{"NOMBRE":"LUCAS","LICENCIA":"18","DORSAL":"9","CODPARTICIPANTE":"26535226","FECHA_NACIMIENTO":1,"PORTERO":null},{"NOMBRE":"CARLOS","LICENCIA":"18","DORSAL":"10","CODPARTICIPANTE":"24253657","FECHA_NACIMIENTO":1,"PORTERO":null},{"NOMBRE":"AGUSTIN","LICENCIA":"18","DORSAL":"11","CODPARTICIPANTE":"23332980","FECHA_NACIMIENTO":1,"PORTERO":null},{"NOMBRE":"NICOLÁS","LICENCIA":"18","DORSAL":"12","CODPARTICIPANTE":"38093970","FECHA_NACIMIENTO":1,"PORTERO":null},{"NOMBRE":"IGNACIO","LICENCIA":"18","DORSAL":"14","CODPARTICIPANTE":"33506471","FECHA_NACIMIENTO":1,"PORTERO":null},{"NOMBRE":"TOMAS","LICENCIA":"18","DORSAL":"15","CODPARTICIPANTE":"18848612","FECHA_NACIMIENTO":1,"PORTERO":null},{"NOMBRE":"JAN","LICENCIA":"18","DORSAL":"17","CODPARTICIPANTE":"20676662","FECHA_NACIMIENTO":1,"PORTERO":null}],"SUPLENTES":[{"NOMBRE":"GUILLEM","LICENCIA":"18","DORSAL":"2","CODPARTICIPANTE":"34969146","FECHA_NACIMIENTO":1,"PORTERO":null},{"NOMBRE":"FABRIZIO","LICENCIA":"18","DORSAL":"4","CODPARTICIPANTE":"27278143","FECHA_NACIMIENTO":1,"PORTERO":null},{"NOMBRE":"FERRAN","LICENCIA":"18","DORSAL":"7","CODPARTICIPANTE":"27306883","FECHA_NACIMIENTO":1,"PORTERO":null},{"NOMBRE":"MIGUEL","LICENCIA":"18","DORSAL":"8","CODPARTICIPANTE":"30554278","FECHA_NACIMIENTO":1,"PORTERO":null},{"NOMBRE":"GUILLERMO","LICENCIA":"18","DORSAL":"13","CODPARTICIPANTE":"32893913","FECHA_NACIMIENTO":1,"PORTERO":1},{"NOMBRE":"ANTONI","LICENCIA":"18","DORSAL":"16","CODPARTICIPANTE":"31668934","FECHA_NACIMIENTO":1,"PORTERO":null},{"NOMBRE":"FRANCISCO JAVIER","LICENCIA":"18","DORSAL":"19","CODPARTICIPANTE":"30177582","FECHA_NACIMIENTO":1,"PORTERO":null},{"NOMBRE":"VICTOR","LICENCIA":"18","DORSAL":"24","CODPARTICIPANTE":"22535107","FECHA_NACIMIENTO":1,"PORTERO":null},{"NOMBRE":"ALEX","LICENCIA":"18","DORSAL":"69","CODPARTICIPANTE":"20039000","FECHA_NACIMIENTO":1,"PORTERO":null}],"COSTECNIC":{"Entrenador Titular":"URBINO","Entrenador Auxiliar":"SERGIO"},"SUSTITUCIONES":[],"SANCIONES":[]},"EQUIPO_FUERA":{"CODCLUB":1051,"CODCLUB2":1051,"CODEQUIPO":36122,"NOMBRE_CLUB":"SANTS, U.E.","NOMBRE_CLUB_URL":"sants-ue","NOMBRE_EQUIPO":"SANTS, U.E. B","NOMBRE_EQUIPO_URL":"sants-ue-b","NOMBRE":"00100_0000671592_uesants_200x200.png","NOMBRE_ABREVIADO_URL":"1c","CODGRUPO":41325884,"TITULARES":[{"NOMBRE":"LLUÍS","LICENCIA":"18","DORSAL":"1","CODPARTICIPANTE":"25103518","FECHA_NACIMIENTO":2,"PORTERO":1},{"NOMBRE":"POL","LICENCIA":"17","DORSAL":"2","CODPARTICIPANTE":"31911135","FECHA_NACIMIENTO":1,"PORTERO":null},{"NOMBRE":"ARNAU","LICENCIA":"17","DORSAL":"4","CODPARTICIPANTE":"22751713","FECHA_NACIMIENTO":1,"PORTERO":null},{"NOMBRE":"JOAN MANEL","LICENCIA":"18","DORSAL":"6","CODPARTICIPANTE":"26675063","FECHA_NACIMIENTO":2,"PORTERO":null},{"NOMBRE":"MARC","LICENCIA":"18","DORSAL":"8","CODPARTICIPANTE":"21223846","FECHA_NACIMIENTO":2,"PORTERO":null},{"NOMBRE":"FERRAN","LICENCIA":"18","DORSAL":"10","CODPARTICIPANTE":"26857237","FECHA_NACIMIENTO":2,"PORTERO":null},{"NOMBRE":"POL","LICENCIA":"18","DORSAL":"11","CODPARTICIPANTE":"20155021","FECHA_NACIMIENTO":2,"PORTERO":null},{"NOMBRE":"ÓSCAR","LICENCIA":"18","DORSAL":"12","CODPARTICIPANTE":"21826250","FECHA_NACIMIENTO":2,"PORTERO":null},{"NOMBRE":"ALEX","LICENCIA":"18","DORSAL":"16","CODPARTICIPANTE":"25819753","FECHA_NACIMIENTO":2,"PORTERO":null},{"NOMBRE":"BERNAT","LICENCIA":"18","DORSAL":"18","CODPARTICIPANTE":"19981889","FECHA_NACIMIENTO":2,"PORTERO":null},{"NOMBRE":"MARTI","LICENCIA":"18","DORSAL":"21","CODPARTICIPANTE":"25959739","FECHA_NACIMIENTO":1,"PORTERO":null}],"SUPLENTES":[{"NOMBRE":"ARNAU","LICENCIA":"18","DORSAL":"3","CODPARTICIPANTE":"19634996","FECHA_NACIMIENTO":2,"PORTERO":null},{"NOMBRE":"JULEN","LICENCIA":"17","DORSAL":"5","CODPARTICIPANTE":"28993244","FECHA_NACIMIENTO":1,"PORTERO":null},{"NOMBRE":"ASIER","LICENCIA":"18","DORSAL":"7","CODPARTICIPANTE":"28910992","FECHA_NACIMIENTO":2,"PORTERO":null},{"NOMBRE":"JOSE RAFAEL","LICENCIA":"18","DORSAL":"13","CODPARTICIPANTE":"34304942","FECHA_NACIMIENTO":2,"PORTERO":1},{"NOMBRE":"ADAM","LICENCIA":"18","DORSAL":"15","CODPARTICIPANTE":"23365612","FECHA_NACIMIENTO":2,"PORTERO":null},{"NOMBRE":"LUCAS","LICENCIA":"18","DORSAL":"20","CODPARTICIPANTE":"29978742","FECHA_NACIMIENTO":1,"PORTERO":null},{"NOMBRE":"EDUARD","LICENCIA":"17","DORSAL":"30","CODPARTICIPANTE":"34821757","FECHA_NACIMIENTO":1,"PORTERO":null}],"COSTECNIC":{"Delegat":"BASILIO","Entrenador Titular":"PAU","Auxiliar":"PEDRO"},"SUSTITUCIONES":[],"SANCIONES":[{"NOMBRE":"FERRAN","LICENCIA":"18","DORSAL":"10","CODPARTICIPANTE":"26857237","FECHA_NACIMIENTO":2,"PORTERO":null,"TIPO":"groga","MINUTO":"65"}]}},"codacta":"3009681","titulars_local":[{"codparticipant":42741389,"codequip":36242,"dorsal":1,"titularitats":1,"porter":1,"nom":"AMMAR","any":2007,"partits":1,"nom_equip":"SARRIA, C.P. A","colorequipacio1":"#FF0000","colorequipacio2":"#FFFF00"},{"codparticipant":34969146,"codequip":36242,"dorsal":2,"titularitats":0,"porter":null,"nom":"GUILLEM","any":2007,"partits":1,"nom_equip":"SARRIA, C.P. A","colorequipacio1":"#FF0000","colorequipacio2":"#FFFF00"},{"codparticipant":23553361,"codequip":36242,"dorsal":3,"titularitats":1,"porter":null,"nom":"JORDI","any":2007,"partits":1,"nom_equip":"SARRIA, C.P. A","colorequipacio1":"#FF0000","colorequipacio2":"#FFFF00"},{"codparticipant":27278143,"codequip":36242,"dorsal":4,"titularitats":0,"porter":null,"nom":"FABRIZIO","any":2007,"partits":1,"nom_equip":"SARRIA, C.P. A","colorequipacio1":"#FF0000","colorequipacio2":"#FFFF00"},{"codparticipant":28485589,"codequip":36242,"dorsal":5,"titularitats":1,"porter":null,"nom":"DAVID","any":2007,"partits":1,"nom_equip":"SARRIA, C.P. A","colorequipacio1":"#FF0000","colorequipacio2":"#FFFF00"},{"codparticipant":18594366,"codequip":36242,"dorsal":6,"titularitats":1,"porter":null,"nom":"JOAN","any":2007,"partits":1,"nom_equip":"SARRIA, C.P. A","colorequipacio1":"#FF0000","colorequipacio2":"#FFFF00"},{"codparticipant":27306883,"codequip":36242,"dorsal":7,"titularitats":0,"porter":null,"nom":"FERRAN","any":2007,"partits":1,"nom_equip":"SARRIA, C.P. A","colorequipacio1":"#FF0000","colorequipacio2":"#FFFF00"},{"codparticipant":30554278,"codequip":36242,"dorsal":8,"titularitats":0,"porter":null,"nom":"MIGUEL","any":2007,"partits":1,"nom_equip":"SARRIA, C.P. A","colorequipacio1":"#FF0000","colorequipacio2":"#FFFF00"},{"codparticipant":26535226,"codequip":36242,"dorsal":9,"titularitats":1,"porter":null,"nom":"LUCAS","any":2007,"partits":1,"nom_equip":"SARRIA, C.P. A","colorequipacio1":"#FF0000","colorequipacio2":"#FFFF00"},{"codparticipant":24253657,"codequip":36242,"dorsal":10,"titularitats":1,"porter":null,"nom":"CARLOS","any":2007,"partits":1,"nom_equip":"SARRIA, C.P. A","colorequipacio1":"#FF0000","colorequipacio2":"#FFFF00"},{"codparticipant":23332980,"codequip":36242,"dorsal":11,"titularitats":1,"porter":null,"nom":"AGUSTIN","any":2007,"partits":1,"nom_equip":"SARRIA, C.P. A","colorequipacio1":"#FF0000","colorequipacio2":"#FFFF00"},{"codparticipant":38093970,"codequip":36242,"dorsal":12,"titularitats":1,"porter":null,"nom":"NICOLÁS","any":2007,"partits":1,"nom_equip":"SARRIA, C.P. A","colorequipacio1":"#FF0000","colorequipacio2":"#FFFF00"},{"codparticipant":32893913,"codequip":36242,"dorsal":13,"titularitats":0,"porter":1,"nom":"GUILLERMO","any":2007,"partits":1,"nom_equip":"SARRIA, C.P. A","colorequipacio1":"#FF0000","colorequipacio2":"#FFFF00"},{"codparticipant":33506471,"codequip":36242,"dorsal":14,"titularitats":1,"porter":null,"nom":"IGNACIO","any":2007,"partits":1,"nom_equip":"SARRIA, C.P. A","colorequipacio1":"#FF0000","colorequipacio2":"#FFFF00"},{"codparticipant":18848612,"codequip":36242,"dorsal":15,"titularitats":1,"porter":null,"nom":"TOMAS","any":2007,"partits":1,"nom_equip":"SARRIA, C.P. A","colorequipacio1":"#FF0000","colorequipacio2":"#FFFF00"},{"codparticipant":31668934,"codequip":36242,"dorsal":16,"titularitats":0,"porter":null,"nom":"ANTONI","any":2007,"partits":1,"nom_equip":"SARRIA, C.P. A","colorequipacio1":"#FF0000","colorequipacio2":"#FFFF00"},{"codparticipant":20676662,"codequip":36242,"dorsal":17,"titularitats":1,"porter":null,"nom":"JAN","any":2007,"partits":1,"nom_equip":"SARRIA, C.P. A","colorequipacio1":"#FF0000","colorequipacio2":"#FFFF00"},{"codparticipant":30177582,"codequip":36242,"dorsal":19,"titularitats":0,"porter":null,"nom":"FRANCISCO JAVIER","any":2007,"partits":1,"nom_equip":"SARRIA, C.P. A","colorequipacio1":"#FF0000","colorequipacio2":"#FFFF00"},{"codparticipant":22535107,"codequip":36242,"dorsal":24,"titularitats":0,"porter":null,"nom":"VICTOR","any":2007,"partits":1,"nom_equip":"SARRIA, C.P. A","colorequipacio1":"#FF0000","colorequipacio2":"#FFFF00"},{"codparticipant":20039000,"codequip":36242,"dorsal":69,"titularitats":0,"porter":null,"nom":"ALEX","any":2007,"partits":1,"nom_equip":"SARRIA, C.P. A","colorequipacio1":"#FF0000","colorequipacio2":"#FFFF00"}],"titulars_visitant":[{"codparticipant":25103518,"codequip":36122,"dorsal":1,"titularitats":1,"porter":1,"nom":"LLUÍS","any":2008,"partits":1,"nom_equip":"SANTS, U.E. B","colorequipacio1":"#FFFFFF","colorequipacio2":"#222222"},{"codparticipant":31911135,"codequip":36122,"dorsal":2,"titularitats":1,"porter":null,"nom":"POL","any":2007,"partits":1,"nom_equip":"SANTS, U.E. B","colorequipacio1":"#FFFFFF","colorequipacio2":"#222222"},{"codparticipant":19634996,"codequip":36122,"dorsal":3,"titularitats":0,"porter":null,"nom":"ARNAU","any":2008,"partits":1,"nom_equip":"SANTS, U.E. B","colorequipacio1":"#FFFFFF","colorequipacio2":"#222222"},{"codparticipant":22751713,"codequip":36122,"dorsal":4,"titularitats":1,"porter":null,"nom":"ARNAU","any":2007,"partits":1,"nom_equip":"SANTS, U.E. B","colorequipacio1":"#FFFFFF","colorequipacio2":"#222222"},{"codparticipant":28993244,"codequip":36122,"dorsal":5,"titularitats":0,"porter":null,"nom":"JULEN","any":2007,"partits":1,"nom_equip":"SANTS, U.E. B","colorequipacio1":"#FFFFFF","colorequipacio2":"#222222"},{"codparticipant":26675063,"codequip":36122,"dorsal":6,"titularitats":1,"porter":null,"nom":"JOAN MANEL","any":2008,"partits":1,"nom_equip":"SANTS, U.E. B","colorequipacio1":"#FFFFFF","colorequipacio2":"#222222"},{"codparticipant":28910992,"codequip":36122,"dorsal":7,"titularitats":0,"porter":null,"nom":"ASIER","any":2008,"partits":1,"nom_equip":"SANTS, U.E. B","colorequipacio1":"#FFFFFF","colorequipacio2":"#222222"},{"codparticipant":21223846,"codequip":36122,"dorsal":8,"titularitats":1,"porter":null,"nom":"MARC","any":2008,"partits":1,"nom_equip":"SANTS, U.E. B","colorequipacio1":"#FFFFFF","colorequipacio2":"#222222"},{"codparticipant":26857237,"codequip":36122,"dorsal":10,"titularitats":1,"porter":null,"nom":"FERRAN","any":2008,"partits":1,"nom_equip":"SANTS, U.E. B","colorequipacio1":"#FFFFFF","colorequipacio2":"#222222"},{"codparticipant":20155021,"codequip":36122,"dorsal":11,"titularitats":1,"porter":null,"nom":"POL","any":2008,"partits":1,"nom_equip":"SANTS, U.E. B","colorequipacio1":"#FFFFFF","colorequipacio2":"#222222"},{"codparticipant":21826250,"codequip":36122,"dorsal":12,"titularitats":1,"porter":null,"nom":"ÓSCAR","any":2008,"partits":1,"nom_equip":"SANTS, U.E. B","colorequipacio1":"#FFFFFF","colorequipacio2":"#222222"},{"codparticipant":34304942,"codequip":36122,"dorsal":13,"titularitats":0,"porter":1,"nom":"JOSE RAFAEL","any":2008,"partits":1,"nom_equip":"SANTS, U.E. B","colorequipacio1":"#FFFFFF","colorequipacio2":"#222222"},{"codparticipant":23365612,"codequip":36122,"dorsal":15,"titularitats":0,"porter":null,"nom":"ADAM","any":2008,"partits":1,"nom_equip":"SANTS, U.E. B","colorequipacio1":"#FFFFFF","colorequipacio2":"#222222"},{"codparticipant":25819753,"codequip":36122,"dorsal":16,"titularitats":1,"porter":null,"nom":"ALEX","any":2008,"partits":1,"nom_equip":"SANTS, U.E. B","colorequipacio1":"#FFFFFF","colorequipacio2":"#222222"},{"codparticipant":19981889,"codequip":36122,"dorsal":18,"titularitats":1,"porter":null,"nom":"BERNAT","any":2008,"partits":1,"nom_equip":"SANTS, U.E. B","colorequipacio1":"#FFFFFF","colorequipacio2":"#222222"},{"codparticipant":29978742,"codequip":36122,"dorsal":20,"titularitats":0,"porter":null,"nom":"LUCAS","any":2007,"partits":1,"nom_equip":"SANTS, U.E. B","colorequipacio1":"#FFFFFF","colorequipacio2":"#222222"},{"codparticipant":25959739,"codequip":36122,"dorsal":21,"titularitats":1,"porter":null,"nom":"MARTI","any":2007,"partits":1,"nom_equip":"SANTS, U.E. B","colorequipacio1":"#FFFFFF","colorequipacio2":"#222222"},{"codparticipant":34821757,"codequip":36122,"dorsal":30,"titularitats":0,"porter":null,"nom":"EDUARD","any":2007,"partits":1,"nom_equip":"SANTS, U.E. B","colorequipacio1":"#FFFFFF","colorequipacio2":"#222222"}],"menuFollowTeams":[{"label":"Cadet A","href":"/classificacio?id=44766647"},{"label":"Cadet B","href":"/classificacio?id=44766583"},{"label":"Cadet C","href":"/classificacio?id=45060588"},{"label":"Cadet D","href":"/classificacio?id=45061869"}]}