{"data":{"INFO":{"CODGRUPO":"44766647","GOLES_CASA":"3","GOLES_FUERA":"1","PENALTIS_CASA":null,"PENALTIS_FUERA":null,"CODACTA":"3009616","COD_COMPETICION":43980440,"NOM_COMPETICION":"CADET PRIMERA DIVISIÓ","NOM_COMPETICION_URL":"cadet-primera-divisio","COD_GRUPO":44766647,"GRUPO":"GRUP 2","GRUPO_URL":"grup-2","CODEQUIPO_CASA":"36069","CODEQUIPO_FUERA":"34219","JORNADA":"7","CODIGO_CAMPO":"515","COMIENZO1":"2022-11-12 20:00:00","SUSPENDIDO":"0","NOMBRE":"CAMP DE FUTBOL MPAL. NARCÍS SALA","DIRECCION":"c/ de Santa Coloma, 39","TEMP_NOMBRE":"2223","TEMP_LARGO":"TEMPORADA 2022-2023","CIUDAD":"Barcelona","ESTADO":"4"},"ARBITROS":[{"CODTIPO_ARBITRO":"1","CODARBITRO":"8333","NOMBRE_ARBITRO":"ADRIAN","NOMBRE":"Barcelona1"}],"GOLES":[{"NOMBRE":"XAVIER","LICENCIA":"18","DORSAL":"7","CODPARTICIPANTE":"22519804","FECHA_NACIMIENTO":2,"PORTERO":null,"TIPO":"normal","MINUTO":"5","EQUIPO":"local"},{"NOMBRE":"SUNKIL","LICENCIA":"18","DORSAL":"10","CODPARTICIPANTE":"39958435","FECHA_NACIMIENTO":2,"PORTERO":null,"TIPO":"normal","MINUTO":"18","EQUIPO":"local"},{"NOMBRE":"ERIK","LICENCIA":"18","DORSAL":"11","CODPARTICIPANTE":"20264163","FECHA_NACIMIENTO":2,"PORTERO":null,"TIPO":"normal","MINUTO":"57","EQUIPO":"local"},{"NOMBRE":"JOEL","LICENCIA":"18","DORSAL":"17","CODPARTICIPANTE":"23311516","FECHA_NACIMIENTO":2,"PORTERO":null,"TIPO":"propia","MINUTO":"27","EQUIPO":"local"}],"EQUIPO_CASA":{"CODCLUB":1014,"CODCLUB2":1014,"CODEQUIPO":36069,"NOMBRE_CLUB":"SANT ANDREU, U.E","NOMBRE_CLUB_URL":"sant-andreu-ue","NOMBRE_EQUIPO":"SANT ANDREU, U.E B","NOMBRE_EQUIPO_URL":"sant-andreu-ue-b","NOMBRE":"00100_0000573790_standreu_200x200.png","NOMBRE_ABREVIADO_URL":"1c","CODGRUPO":40987548,"TITULARES":[{"NOMBRE":"IKER","LICENCIA":"18","DORSAL":"1","CODPARTICIPANTE":"21558192","FECHA_NACIMIENTO":2,"PORTERO":1},{"NOMBRE":"TIGRAN NAREK","LICENCIA":"18","DORSAL":"3","CODPARTICIPANTE":"19639973","FECHA_NACIMIENTO":2,"PORTERO":null},{"NOMBRE":"ALEIX","LICENCIA":"18","DORSAL":"4","CODPARTICIPANTE":"20475682","FECHA_NACIMIENTO":2,"PORTERO":null},{"NOMBRE":"GUILLEM","LICENCIA":"18","DORSAL":"5","CODPARTICIPANTE":"19869524","FECHA_NACIMIENTO":2,"PORTERO":null},{"NOMBRE":"ÀLEX","LICENCIA":"18","DORSAL":"6","CODPARTICIPANTE":"19177217","FECHA_NACIMIENTO":2,"PORTERO":null},{"NOMBRE":"XAVIER","LICENCIA":"18","DORSAL":"7","CODPARTICIPANTE":"22519804","FECHA_NACIMIENTO":2,"PORTERO":null},{"NOMBRE":"TONI","LICENCIA":"18","DORSAL":"8","CODPARTICIPANTE":"19663520","FECHA_NACIMIENTO":2,"PORTERO":null},{"NOMBRE":"SUNKIL","LICENCIA":"18","DORSAL":"10","CODPARTICIPANTE":"39958435","FECHA_NACIMIENTO":2,"PORTERO":null},{"NOMBRE":"JOEL","LICENCIA":"18","DORSAL":"17","CODPARTICIPANTE":"23311516","FECHA_NACIMIENTO":2,"PORTERO":null},{"NOMBRE":"PAU","LICENCIA":"18","DORSAL":"21","CODPARTICIPANTE":"26535085","FECHA_NACIMIENTO":2,"PORTERO":null},{"NOMBRE":"MARTI","LICENCIA":"18","DORSAL":"51","CODPARTICIPANTE":"18764153","FECHA_NACIMIENTO":2,"PORTERO":null}],"SUPLENTES":[{"NOMBRE":"PAU","LICENCIA":"18","DORSAL":"2","CODPARTICIPANTE":"40604374","FECHA_NACIMIENTO":2,"PORTERO":null},{"NOMBRE":"ERIK","LICENCIA":"18","DORSAL":"11","CODPARTICIPANTE":"20264163","FECHA_NACIMIENTO":2,"PORTERO":null},{"NOMBRE":"ROGER","LICENCIA":"18","DORSAL":"12","CODPARTICIPANTE":"20675835","FECHA_NACIMIENTO":2,"PORTERO":null},{"NOMBRE":"YAKOV","LICENCIA":"18","DORSAL":"13","CODPARTICIPANTE":"33185896","FECHA_NACIMIENTO":2,"PORTERO":1},{"NOMBRE":"ANTHONY ANDREU","LICENCIA":"18","DORSAL":"15","CODPARTICIPANTE":"19944339","FECHA_NACIMIENTO":2,"PORTERO":null},{"NOMBRE":"JOAQUIM","LICENCIA":"18","DORSAL":"18","CODPARTICIPANTE":"20141088","FECHA_NACIMIENTO":2,"PORTERO":null},{"NOMBRE":"PAU","LICENCIA":"18","DORSAL":"19","CODPARTICIPANTE":"21785040","FECHA_NACIMIENTO":2,"PORTERO":null}],"COSTECNIC":{"Entrenador Titular":"POL","Delegat":"ROGER"},"SUSTITUCIONES":[],"SANCIONES":[{"NOMBRE":"ERIK","LICENCIA":"18","DORSAL":"11","CODPARTICIPANTE":"20264163","FECHA_NACIMIENTO":2,"PORTERO":null,"TIPO":"groga","MINUTO":"78"},{"NOMBRE":"YAKOV","LICENCIA":"18","DORSAL":"13","CODPARTICIPANTE":"33185896","FECHA_NACIMIENTO":2,"PORTERO":1,"TIPO":"groga","MINUTO":"54"}]},"EQUIPO_FUERA":{"CODCLUB":2670,"CODCLUB2":2670,"CODEQUIPO":34219,"NOMBRE_CLUB":"ESCOLA COLLBLANC-TORRASSA,C.E","NOMBRE_CLUB_URL":"escola-collblanc-torrassa-ce","NOMBRE_EQUIPO":"ESCOLA COLLBLANC-TORRASSA,C.E A","NOMBRE_EQUIPO_URL":"escola-collblanc-torrassa-ce-a","NOMBRE":"00100_0000003500_images.png","NOMBRE_ABREVIADO_URL":"1c","CODGRUPO":41325917,"TITULARES":[{"NOMBRE":"JOSE DAVID","LICENCIA":"18","DORSAL":"1","CODPARTICIPANTE":"23397515","FECHA_NACIMIENTO":2,"PORTERO":1},{"NOMBRE":"ADRIAN","LICENCIA":"18","DORSAL":"3","CODPARTICIPANTE":"39370965","FECHA_NACIMIENTO":2,"PORTERO":null},{"NOMBRE":"MARC","LICENCIA":"18","DORSAL":"5","CODPARTICIPANTE":"35863604","FECHA_NACIMIENTO":1,"PORTERO":null},{"NOMBRE":"LUCAS","LICENCIA":"18","DORSAL":"6","CODPARTICIPANTE":"24095515","FECHA_NACIMIENTO":1,"PORTERO":null},{"NOMBRE":"IAN","LICENCIA":"18","DORSAL":"7","CODPARTICIPANTE":"25241556","FECHA_NACIMIENTO":1,"PORTERO":null},{"NOMBRE":"JOAO EDUARDO","LICENCIA":"18","DORSAL":"9","CODPARTICIPANTE":"22467031","FECHA_NACIMIENTO":2,"PORTERO":null},{"NOMBRE":"MARTIN","LICENCIA":"18","DORSAL":"10","CODPARTICIPANTE":"23338976","FECHA_NACIMIENTO":2,"PORTERO":null},{"NOMBRE":"JORDI SALVADOR","LICENCIA":"18","DORSAL":"11","CODPARTICIPANTE":"22868649","FECHA_NACIMIENTO":2,"PORTERO":null},{"NOMBRE":"JUAN JOSE","LICENCIA":"18","DORSAL":"12","CODPARTICIPANTE":"33749941","FECHA_NACIMIENTO":1,"PORTERO":null},{"NOMBRE":"ALAN","LICENCIA":"18","DORSAL":"16","CODPARTICIPANTE":"45947502","FECHA_NACIMIENTO":2,"PORTERO":null},{"NOMBRE":"HICHAM","LICENCIA":"18","DORSAL":"17","CODPARTICIPANTE":"33499843","FECHA_NACIMIENTO":1,"PORTERO":null}],"SUPLENTES":[{"NOMBRE":"VICTOR","LICENCIA":"18","DORSAL":"4","CODPARTICIPANTE":"23305734","FECHA_NACIMIENTO":2,"PORTERO":null},{"NOMBRE":"JOAN","LICENCIA":"18","DORSAL":"8","CODPARTICIPANTE":"23602478","FECHA_NACIMIENTO":2,"PORTERO":null},{"NOMBRE":"HOVHANNES","LICENCIA":"18","DORSAL":"14","CODPARTICIPANTE":"27366457","FECHA_NACIMIENTO":2,"PORTERO":null},{"NOMBRE":"OMAR","LICENCIA":"18","DORSAL":"15","CODPARTICIPANTE":"35834408","FECHA_NACIMIENTO":1,"PORTERO":null},{"NOMBRE":"HUGO","LICENCIA":"18","DORSAL":"18","CODPARTICIPANTE":"35129910","FECHA_NACIMIENTO":1,"PORTERO":null},{"NOMBRE":"MOHAMED","LICENCIA":"18","DORSAL":"19","CODPARTICIPANTE":"37128840","FECHA_NACIMIENTO":1,"PORTERO":null}],"COSTECNIC":{"Delegat":"JUAN MANUEL","Entrenador Titular":"FCO.JAVIER"},"SUSTITUCIONES":[],"SANCIONES":[{"NOMBRE":"MOHAMED","LICENCIA":"18","DORSAL":"19","CODPARTICIPANTE":"37128840","FECHA_NACIMIENTO":1,"PORTERO":null,"TIPO":"groga","MINUTO":"79"}]}},"codacta":"3009616","titulars_local":[{"codparticipant":21558192,"codequip":36069,"dorsal":1,"titularitats":1,"porter":1,"nom":"IKER","any":2008,"partits":1,"nom_equip":"SANT ANDREU, U.E B","colorequipacio1":"#FFFF00","colorequipacio2":"#0000FF"},{"codparticipant":40604374,"codequip":36069,"dorsal":2,"titularitats":0,"porter":null,"nom":"PAU","any":2008,"partits":1,"nom_equip":"SANT ANDREU, U.E B","colorequipacio1":"#FFFF00","colorequipacio2":"#0000FF"},{"codparticipant":19639973,"codequip":36069,"dorsal":3,"titularitats":1,"porter":null,"nom":"TIGRAN NAREK","any":2008,"partits":1,"nom_equip":"SANT ANDREU, U.E B","colorequipacio1":"#FFFF00","colorequipacio2":"#0000FF"},{"codparticipant":20475682,"codequip":36069,"dorsal":4,"titularitats":1,"porter":null,"nom":"ALEIX","any":2008,"partits":1,"nom_equip":"SANT ANDREU, U.E B","colorequipacio1":"#FFFF00","colorequipacio2":"#0000FF"},{"codparticipant":19869524,"codequip":36069,"dorsal":5,"titularitats":1,"porter":null,"nom":"GUILLEM","any":2008,"partits":1,"nom_equip":"SANT ANDREU, U.E B","colorequipacio1":"#FFFF00","colorequipacio2":"#0000FF"},{"codparticipant":19177217,"codequip":36069,"dorsal":6,"titularitats":1,"porter":null,"nom":"ÀLEX","any":2008,"partits":1,"nom_equip":"SANT ANDREU, U.E B","colorequipacio1":"#FFFF00","colorequipacio2":"#0000FF"},{"codparticipant":22519804,"codequip":36069,"dorsal":7,"titularitats":1,"porter":null,"nom":"XAVIER","any":2008,"partits":1,"nom_equip":"SANT ANDREU, U.E B","colorequipacio1":"#FFFF00","colorequipacio2":"#0000FF"},{"codparticipant":19663520,"codequip":36069,"dorsal":8,"titularitats":1,"porter":null,"nom":"TONI","any":2008,"partits":1,"nom_equip":"SANT ANDREU, U.E B","colorequipacio1":"#FFFF00","colorequipacio2":"#0000FF"},{"codparticipant":39958435,"codequip":36069,"dorsal":10,"titularitats":1,"porter":null,"nom":"SUNKIL","any":2008,"partits":1,"nom_equip":"SANT ANDREU, U.E B","colorequipacio1":"#FFFF00","colorequipacio2":"#0000FF"},{"codparticipant":20264163,"codequip":36069,"dorsal":11,"titularitats":0,"porter":null,"nom":"ERIK","any":2008,"partits":1,"nom_equip":"SANT ANDREU, U.E B","colorequipacio1":"#FFFF00","colorequipacio2":"#0000FF"},{"codparticipant":20675835,"codequip":36069,"dorsal":12,"titularitats":0,"porter":null,"nom":"ROGER","any":2008,"partits":1,"nom_equip":"SANT ANDREU, U.E B","colorequipacio1":"#FFFF00","colorequipacio2":"#0000FF"},{"codparticipant":33185896,"codequip":36069,"dorsal":13,"titularitats":0,"porter":1,"nom":"YAKOV","any":2008,"partits":1,"nom_equip":"SANT ANDREU, U.E B","colorequipacio1":"#FFFF00","colorequipacio2":"#0000FF"},{"codparticipant":19944339,"codequip":36069,"dorsal":15,"titularitats":0,"porter":null,"nom":"ANTHONY ANDREU","any":2008,"partits":1,"nom_equip":"SANT ANDREU, U.E B","colorequipacio1":"#FFFF00","colorequipacio2":"#0000FF"},{"codparticipant":23311516,"codequip":36069,"dorsal":17,"titularitats":1,"porter":null,"nom":"JOEL","any":2008,"partits":1,"nom_equip":"SANT ANDREU, U.E B","colorequipacio1":"#FFFF00","colorequipacio2":"#0000FF"},{"codparticipant":20141088,"codequip":36069,"dorsal":18,"titularitats":0,"porter":null,"nom":"JOAQUIM","any":2008,"partits":1,"nom_equip":"SANT ANDREU, U.E B","colorequipacio1":"#FFFF00","colorequipacio2":"#0000FF"},{"codparticipant":21785040,"codequip":36069,"dorsal":19,"titularitats":0,"porter":null,"nom":"PAU","any":2008,"partits":1,"nom_equip":"SANT ANDREU, U.E B","colorequipacio1":"#FFFF00","colorequipacio2":"#0000FF"},{"codparticipant":26535085,"codequip":36069,"dorsal":21,"titularitats":1,"porter":null,"nom":"PAU","any":2008,"partits":1,"nom_equip":"SANT ANDREU, U.E B","colorequipacio1":"#FFFF00","colorequipacio2":"#0000FF"},{"codparticipant":18764153,"codequip":36069,"dorsal":51,"titularitats":1,"porter":null,"nom":"MARTI","any":2008,"partits":1,"nom_equip":"SANT ANDREU, U.E B","colorequipacio1":"#FFFF00","colorequipacio2":"#0000FF"}],"titulars_visitant":[{"codparticipant":23397515,"codequip":34219,"dorsal":1,"titularitats":1,"porter":1,"nom":"JOSE DAVID","any":2008,"partits":1,"nom_equip":"ESCOLA COLLBLANC-TORRASSA,C.E A","colorequipacio1":"#263CFF","colorequipacio2":"#FF0000"},{"codparticipant":39370965,"codequip":34219,"dorsal":3,"titularitats":1,"porter":null,"nom":"ADRIAN","any":2008,"partits":1,"nom_equip":"ESCOLA COLLBLANC-TORRASSA,C.E A","colorequipacio1":"#263CFF","colorequipacio2":"#FF0000"},{"codparticipant":23305734,"codequip":34219,"dorsal":4,"titularitats":0,"porter":null,"nom":"VICTOR","any":2008,"partits":1,"nom_equip":"ESCOLA COLLBLANC-TORRASSA,C.E A","colorequipacio1":"#263CFF","colorequipacio2":"#FF0000"},{"codparticipant":35863604,"codequip":34219,"dorsal":5,"titularitats":1,"porter":null,"nom":"MARC","any":2007,"partits":1,"nom_equip":"ESCOLA COLLBLANC-TORRASSA,C.E A","colorequipacio1":"#263CFF","colorequipacio2":"#FF0000"},{"codparticipant":24095515,"codequip":34219,"dorsal":6,"titularitats":1,"porter":null,"nom":"LUCAS","any":2007,"partits":1,"nom_equip":"ESCOLA COLLBLANC-TORRASSA,C.E A","colorequipacio1":"#263CFF","colorequipacio2":"#FF0000"},{"codparticipant":25241556,"codequip":34219,"dorsal":7,"titularitats":1,"porter":null,"nom":"IAN","any":2007,"partits":1,"nom_equip":"ESCOLA COLLBLANC-TORRASSA,C.E A","colorequipacio1":"#263CFF","colorequipacio2":"#FF0000"},{"codparticipant":23602478,"codequip":34219,"dorsal":8,"titularitats":0,"porter":null,"nom":"JOAN","any":2008,"partits":1,"nom_equip":"ESCOLA COLLBLANC-TORRASSA,C.E A","colorequipacio1":"#263CFF","colorequipacio2":"#FF0000"},{"codparticipant":22467031,"codequip":34219,"dorsal":9,"titularitats":1,"porter":null,"nom":"JOAO EDUARDO","any":2008,"partits":1,"nom_equip":"ESCOLA COLLBLANC-TORRASSA,C.E A","colorequipacio1":"#263CFF","colorequipacio2":"#FF0000"},{"codparticipant":23338976,"codequip":34219,"dorsal":10,"titularitats":1,"porter":null,"nom":"MARTIN","any":2008,"partits":1,"nom_equip":"ESCOLA COLLBLANC-TORRASSA,C.E A","colorequipacio1":"#263CFF","colorequipacio2":"#FF0000"},{"codparticipant":22868649,"codequip":34219,"dorsal":11,"titularitats":1,"porter":null,"nom":"JORDI SALVADOR","any":2008,"partits":1,"nom_equip":"ESCOLA COLLBLANC-TORRASSA,C.E A","colorequipacio1":"#263CFF","colorequipacio2":"#FF0000"},{"codparticipant":33749941,"codequip":34219,"dorsal":12,"titularitats":1,"porter":null,"nom":"JUAN JOSE","any":2007,"partits":1,"nom_equip":"ESCOLA COLLBLANC-TORRASSA,C.E A","colorequipacio1":"#263CFF","colorequipacio2":"#FF0000"},{"codparticipant":27366457,"codequip":34219,"dorsal":14,"titularitats":0,"porter":null,"nom":"HOVHANNES","any":2008,"partits":1,"nom_equip":"ESCOLA COLLBLANC-TORRASSA,C.E A","colorequipacio1":"#263CFF","colorequipacio2":"#FF0000"},{"codparticipant":35834408,"codequip":34219,"dorsal":15,"titularitats":0,"porter":null,"nom":"OMAR","any":2007,"partits":1,"nom_equip":"ESCOLA COLLBLANC-TORRASSA,C.E A","colorequipacio1":"#263CFF","colorequipacio2":"#FF0000"},{"codparticipant":45947502,"codequip":34219,"dorsal":16,"titularitats":1,"porter":null,"nom":"ALAN","any":2008,"partits":1,"nom_equip":"ESCOLA COLLBLANC-TORRASSA,C.E A","colorequipacio1":"#263CFF","colorequipacio2":"#FF0000"},{"codparticipant":33499843,"codequip":34219,"dorsal":17,"titularitats":1,"porter":null,"nom":"HICHAM","any":2007,"partits":1,"nom_equip":"ESCOLA COLLBLANC-TORRASSA,C.E A","colorequipacio1":"#263CFF","colorequipacio2":"#FF0000"},{"codparticipant":35129910,"codequip":34219,"dorsal":18,"titularitats":0,"porter":null,"nom":"HUGO","any":2007,"partits":1,"nom_equip":"ESCOLA COLLBLANC-TORRASSA,C.E A","colorequipacio1":"#263CFF","colorequipacio2":"#FF0000"},{"codparticipant":37128840,"codequip":34219,"dorsal":19,"titularitats":0,"porter":null,"nom":"MOHAMED","any":2007,"partits":1,"nom_equip":"ESCOLA COLLBLANC-TORRASSA,C.E A","colorequipacio1":"#263CFF","colorequipacio2":"#FF0000"}],"menuFollowTeams":[{"label":"Cadet A","href":"/classificacio?id=44766647"},{"label":"Cadet B","href":"/classificacio?id=44766583"},{"label":"Cadet C","href":"/classificacio?id=45060588"},{"label":"Cadet D","href":"/classificacio?id=45061869"}]}