{"data":{"INFO":{"CODGRUPO":"45060588","GOLES_CASA":"4","GOLES_FUERA":"0","PENALTIS_CASA":null,"PENALTIS_FUERA":null,"CODACTA":"3042764","COD_COMPETICION":43980441,"NOM_COMPETICION":"CADET SEGONA DIVISIÓ","NOM_COMPETICION_URL":"cadet-segona-divisio","COD_GRUPO":45060588,"GRUPO":"GRUP 18","GRUPO_URL":"grup-18","CODEQUIPO_CASA":"38038","CODEQUIPO_FUERA":"25909655","JORNADA":"7","CODIGO_CAMPO":"544","COMIENZO1":"2022-11-19 14:30:00","SUSPENDIDO":"1","NOMBRE":"CAMP DE FUTBOL MPAL. SANT GENÍS","DIRECCION":"c/ de Samaria nº 12","TEMP_NOMBRE":"2223","TEMP_LARGO":"TEMPORADA 2022-2023","CIUDAD":"Barcelona","ESTADO":"4"},"ARBITROS":[{"CODTIPO_ARBITRO":"1","CODARBITRO":"3327801","NOMBRE_ARBITRO":"LUCAS","NOMBRE":"Barcelona3"}],"GOLES":[{"NOMBRE":"ALEX","LICENCIA":"18","DORSAL":"10","CODPARTICIPANTE":"20131387","FECHA_NACIMIENTO":1,"PORTERO":null,"TIPO":"normal","MINUTO":"2","EQUIPO":"local"},{"NOMBRE":"ALEX","LICENCIA":"18","DORSAL":"10","CODPARTICIPANTE":"20131387","FECHA_NACIMIENTO":1,"PORTERO":null,"TIPO":"normal","MINUTO":"15","EQUIPO":"local"},{"NOMBRE":"ALEX","LICENCIA":"18","DORSAL":"10","CODPARTICIPANTE":"20131387","FECHA_NACIMIENTO":1,"PORTERO":null,"TIPO":"normal","MINUTO":"20","EQUIPO":"local"},{"NOMBRE":"VICTOR","LICENCIA":"18","DORSAL":"14","CODPARTICIPANTE":"32612827","FECHA_NACIMIENTO":1,"PORTERO":null,"TIPO":"normal","MINUTO":"1","EQUIPO":"local"}],"EQUIPO_CASA":{"CODCLUB":1214,"CODCLUB2":1214,"CODEQUIPO":38038,"NOMBRE_CLUB":"Pª BARC. VILLAVERDE-PENITENTS","NOMBRE_CLUB_URL":"pa-barc-villaverde-penitents","NOMBRE_EQUIPO":"Pª BARC. VILLAVERDE-PENITENTS A","NOMBRE_EQUIPO_URL":"pa-barc-villaverde-penitents-a","NOMBRE":"00100_0000012218_Villaverde pequeno.png","NOMBRE_ABREVIADO_URL":"2c","CODGRUPO":41819620,"TITULARES":[{"NOMBRE":"NIL","LICENCIA":"18","DORSAL":"3","CODPARTICIPANTE":"31976047","FECHA_NACIMIENTO":1,"PORTERO":null},{"NOMBRE":"ARNAU","LICENCIA":"18","DORSAL":"4","CODPARTICIPANTE":"30353520","FECHA_NACIMIENTO":2,"PORTERO":null},{"NOMBRE":"NICOLAS","LICENCIA":"18","DORSAL":"6","CODPARTICIPANTE":"33105557","FECHA_NACIMIENTO":1,"PORTERO":null},{"NOMBRE":"ALEX","LICENCIA":"18","DORSAL":"10","CODPARTICIPANTE":"20131387","FECHA_NACIMIENTO":1,"PORTERO":null},{"NOMBRE":"JAN","LICENCIA":"18","DORSAL":"11","CODPARTICIPANTE":"30106487","FECHA_NACIMIENTO":2,"PORTERO":null},{"NOMBRE":"JANUSZ","LICENCIA":"18","DORSAL":"12","CODPARTICIPANTE":"27061166","FECHA_NACIMIENTO":2,"PORTERO":null},{"NOMBRE":"VICTOR","LICENCIA":"18","DORSAL":"14","CODPARTICIPANTE":"32612827","FECHA_NACIMIENTO":1,"PORTERO":null},{"NOMBRE":"CARLES","LICENCIA":"18","DORSAL":"16","CODPARTICIPANTE":"45401374","FECHA_NACIMIENTO":2,"PORTERO":null},{"NOMBRE":"IZAN","LICENCIA":"18","DORSAL":"25","CODPARTICIPANTE":"29817443","FECHA_NACIMIENTO":2,"PORTERO":1},{"NOMBRE":"ERIC","LICENCIA":"18","DORSAL":"30","CODPARTICIPANTE":"45540851","FECHA_NACIMIENTO":1,"PORTERO":null},{"NOMBRE":"BIEL","LICENCIA":"18","DORSAL":"72","CODPARTICIPANTE":"29776806","FECHA_NACIMIENTO":1,"PORTERO":null}],"SUPLENTES":[{"NOMBRE":"WALID","LICENCIA":"18","DORSAL":"2","CODPARTICIPANTE":"33311120","FECHA_NACIMIENTO":1,"PORTERO":null},{"NOMBRE":"HUGO","LICENCIA":"18","DORSAL":"5","CODPARTICIPANTE":"45401209","FECHA_NACIMIENTO":1,"PORTERO":null},{"NOMBRE":"EDGAR","LICENCIA":"18","DORSAL":"7","CODPARTICIPANTE":"31044067","FECHA_NACIMIENTO":1,"PORTERO":null},{"NOMBRE":"ARTURO","LICENCIA":"18","DORSAL":"9","CODPARTICIPANTE":"32946573","FECHA_NACIMIENTO":1,"PORTERO":null},{"NOMBRE":"LUCAS","LICENCIA":"18","DORSAL":"17","CODPARTICIPANTE":"38921689","FECHA_NACIMIENTO":2,"PORTERO":null},{"NOMBRE":"JOAN DANIEL","LICENCIA":"18","DORSAL":"20","CODPARTICIPANTE":"45399851","FECHA_NACIMIENTO":2,"PORTERO":null}],"COSTECNIC":{"Delegat":"JAVIER","Auxiliar":"PAU"},"SUSTITUCIONES":[],"SANCIONES":[]},"EQUIPO_FUERA":{"CODCLUB":6165,"CODCLUB2":6165,"CODEQUIPO":25909655,"NOMBRE_CLUB":"PENYA BLAUGRANA TRINITAT VELLA","NOMBRE_CLUB_URL":"penya-blaugrana-trinitat-vella","NOMBRE_EQUIPO":"PENYA BLAUGRANA TRINITAT VELLA A","NOMBRE_EQUIPO_URL":"penya-blaugrana-trinitat-vella-a","NOMBRE":"00100_0000162377_ESCUDO_FINAL.png","NOMBRE_ABREVIADO_URL":"2c","CODGRUPO":45060588,"TITULARES":[{"NOMBRE":"DAVID","LICENCIA":"18","DORSAL":"4","CODPARTICIPANTE":"20059941","FECHA_NACIMIENTO":1,"PORTERO":null},{"NOMBRE":"GEIDERBELT JOSE","LICENCIA":"17","DORSAL":"13","CODPARTICIPANTE":"39336201","FECHA_NACIMIENTO":2,"PORTERO":1},{"NOMBRE":"ADAM","LICENCIA":"18","DORSAL":"26","CODPARTICIPANTE":"22868472","FECHA_NACIMIENTO":2,"PORTERO":null},{"NOMBRE":"LUIS FERNANDO","LICENCIA":"18","DORSAL":"73","CODPARTICIPANTE":"36303713","FECHA_NACIMIENTO":2,"PORTERO":null},{"NOMBRE":"ISHAK","LICENCIA":"18","DORSAL":"76","CODPARTICIPANTE":"23545789","FECHA_NACIMIENTO":2,"PORTERO":null},{"NOMBRE":"BILAL AHMAD","LICENCIA":"17","DORSAL":"78","CODPARTICIPANTE":"45863232","FECHA_NACIMIENTO":2,"PORTERO":null},{"NOMBRE":"MUHAMMAD ARON","LICENCIA":"18","DORSAL":"79","CODPARTICIPANTE":"45691256","FECHA_NACIMIENTO":2,"PORTERO":null},{"NOMBRE":"ZAID","LICENCIA":"18","DORSAL":"93","CODPARTICIPANTE":"30118790","FECHA_NACIMIENTO":2,"PORTERO":null}],"SUPLENTES":[],"COSTECNIC":{"Auxiliar":"RONALD ANDRES"},"SUSTITUCIONES":[],"SANCIONES":[]}},"codacta":"3042764","titulars_local":[{"codparticipant":33311120,"codequip":38038,"dorsal":2,"titularitats":0,"porter":null,"nom":"WALID","any":2007,"partits":1,"nom_equip":"Pª BARC. VILLAVERDE-PENITENTS A","colorequipacio1":"#FF0000","colorequipacio2":"#222222"},{"codparticipant":31976047,"codequip":38038,"dorsal":3,"titularitats":1,"porter":null,"nom":"NIL","any":2007,"partits":1,"nom_equip":"Pª BARC. VILLAVERDE-PENITENTS A","colorequipacio1":"#FF0000","colorequipacio2":"#222222"},{"codparticipant":30353520,"codequip":38038,"dorsal":4,"titularitats":1,"porter":null,"nom":"ARNAU","any":2008,"partits":1,"nom_equip":"Pª BARC. VILLAVERDE-PENITENTS A","colorequipacio1":"#FF0000","colorequipacio2":"#222222"},{"codparticipant":45401209,"codequip":38038,"dorsal":5,"titularitats":0,"porter":null,"nom":"HUGO","any":2007,"partits":1,"nom_equip":"Pª BARC. VILLAVERDE-PENITENTS A","colorequipacio1":"#FF0000","colorequipacio2":"#222222"},{"codparticipant":33105557,"codequip":38038,"dorsal":6,"titularitats":1,"porter":null,"nom":"NICOLAS","any":2007,"partits":1,"nom_equip":"Pª BARC. VILLAVERDE-PENITENTS A","colorequipacio1":"#FF0000","colorequipacio2":"#222222"},{"codparticipant":31044067,"codequip":38038,"dorsal":7,"titularitats":0,"porter":null,"nom":"EDGAR","any":2007,"partits":1,"nom_equip":"Pª BARC. VILLAVERDE-PENITENTS A","colorequipacio1":"#FF0000","colorequipacio2":"#222222"},{"codparticipant":32946573,"codequip":38038,"dorsal":9,"titularitats":0,"porter":null,"nom":"ARTURO","any":2007,"partits":1,"nom_equip":"Pª BARC. VILLAVERDE-PENITENTS A","colorequipacio1":"#FF0000","colorequipacio2":"#222222"},{"codparticipant":20131387,"codequip":38038,"dorsal":10,"titularitats":1,"porter":null,"nom":"ALEX","any":2007,"partits":1,"nom_equip":"Pª BARC. VILLAVERDE-PENITENTS A","colorequipacio1":"#FF0000","colorequipacio2":"#222222"},{"codparticipant":30106487,"codequip":38038,"dorsal":11,"titularitats":1,"porter":null,"nom":"JAN","any":2008,"partits":1,"nom_equip":"Pª BARC. VILLAVERDE-PENITENTS A","colorequipacio1":"#FF0000","colorequipacio2":"#222222"},{"codparticipant":27061166,"codequip":38038,"dorsal":12,"titularitats":1,"porter":null,"nom":"JANUSZ","any":2008,"partits":1,"nom_equip":"Pª BARC. VILLAVERDE-PENITENTS A","colorequipacio1":"#FF0000","colorequipacio2":"#222222"},{"codparticipant":32612827,"codequip":38038,"dorsal":14,"titularitats":1,"porter":null,"nom":"VICTOR","any":2007,"partits":1,"nom_equip":"Pª BARC. VILLAVERDE-PENITENTS A","colorequipacio1":"#FF0000","colorequipacio2":"#222222"},{"codparticipant":45401374,"codequip":38038,"dorsal":16,"titularitats":1,"porter":null,"nom":"CARLES","any":2008,"partits":1,"nom_equip":"Pª BARC. VILLAVERDE-PENITENTS A","colorequipacio1":"#FF0000","colorequipacio2":"#222222"},{"codparticipant":38921689,"codequip":38038,"dorsal":17,"titularitats":0,"porter":null,"nom":"LUCAS","any":2008,"partits":1,"nom_equip":"Pª BARC. VILLAVERDE-PENITENTS A","colorequipacio1":"#FF0000","colorequipacio2":"#222222"},{"codparticipant":45399851,"codequip":38038,"dorsal":20,"titularitats":0,"porter":null,"nom":"JOAN DANIEL","any":2008,"partits":1,"nom_equip":"Pª BARC. VILLAVERDE-PENITENTS A","colorequipacio1":"#FF0000","colorequipacio2":"#222222"},{"codparticipant":29817443,"codequip":38038,"dorsal":25,"titularitats":1,"porter":1,"nom":"IZAN","any":2008,"partits":1,"nom_equip":"Pª BARC. VILLAVERDE-PENITENTS A","colorequipacio1":"#FF0000","colorequipacio2":"#222222"},{"codparticipant":45540851,"codequip":38038,"dorsal":30,"titularitats":1,"porter":null,"nom":"ERIC","any":2007,"partits":1,"nom_equip":"Pª BARC. VILLAVERDE-PENITENTS A","colorequipacio1":"#FF0000","colorequipacio2":"#222222"},{"codparticipant":29776806,"codequip":38038,"dorsal":72,"titularitats":1,"porter":null,"nom":"BIEL","any":2007,"partits":1,"nom_equip":"Pª BARC. VILLAVERDE-PENITENTS A","colorequipacio1":"#FF0000","colorequipacio2":"#222222"}],"titulars_visitant":[{"codparticipant":20059941,"codequip":25909655,"dorsal":4,"titularitats":1,"porter":null,"nom":"DAVID","any":2007,"partits":1,"nom_equip":"PENYA BLAUGRANA TRINITAT VELLA A","colorequipacio1":null,"colorequipacio2":null},{"codparticipant":39336201,"codequip":25909655,"dorsal":13,"titularitats":1,"porter":1,"nom":"GEIDERBELT JOSE","any":2008,"partits":1,"nom_equip":"PENYA BLAUGRANA TRINITAT VELLA A","colorequipacio1":null,"colorequipacio2":null},{"codparticipant":22868472,"codequip":25909655,"dorsal":26,"titularitats":1,"porter":null,"nom":"ADAM","any":2008,"partits":1,"nom_equip":"PENYA BLAUGRANA TRINITAT VELLA A","colorequipacio1":null,"colorequipacio2":null},{"codparticipant":36303713,"codequip":25909655,"dorsal":73,"titularitats":1,"porter":null,"nom":"LUIS FERNANDO","any":2008,"partits":1,"nom_equip":"PENYA BLAUGRANA TRINITAT VELLA A","colorequipacio1":null,"colorequipacio2":null},{"codparticipant":23545789,"codequip":25909655,"dorsal":76,"titularitats":1,"porter":null,"nom":"ISHAK","any":2008,"partits":1,"nom_equip":"PENYA BLAUGRANA TRINITAT VELLA A","colorequipacio1":null,"colorequipacio2":null},{"codparticipant":45863232,"codequip":25909655,"dorsal":78,"titularitats":1,"porter":null,"nom":"BILAL AHMAD","any":2008,"partits":1,"nom_equip":"PENYA BLAUGRANA TRINITAT VELLA A","colorequipacio1":null,"colorequipacio2":null},{"codparticipant":45691256,"codequip":25909655,"dorsal":79,"titularitats":1,"porter":null,"nom":"MUHAMMAD ARON","any":2008,"partits":1,"nom_equip":"PENYA BLAUGRANA TRINITAT VELLA A","colorequipacio1":null,"colorequipacio2":null},{"codparticipant":30118790,"codequip":25909655,"dorsal":93,"titularitats":1,"porter":null,"nom":"ZAID","any":2008,"partits":1,"nom_equip":"PENYA BLAUGRANA TRINITAT VELLA A","colorequipacio1":null,"colorequipacio2":null}],"menuFollowTeams":[{"label":"Cadet A","href":"/classificacio?id=44766647"},{"label":"Cadet B","href":"/classificacio?id=44766583"},{"label":"Cadet C","href":"/classificacio?id=45060588"},{"label":"Cadet D","href":"/classificacio?id=45061869"}]}