{"data":[{"codparticipant":20134693,"codequip":38038,"dorsal":1,"titularitats":7,"porter":1,"nom":"IZAN","any":2007,"partits":8,"nom_equip":"Pª BARC. VILLAVERDE-PENITENTS A"},{"codparticipant":32946573,"codequip":38038,"dorsal":4,"titularitats":4,"porter":null,"nom":"ARTURO","any":2007,"partits":10,"nom_equip":"Pª BARC. VILLAVERDE-PENITENTS A"},{"codparticipant":45399851,"codequip":38038,"dorsal":7,"titularitats":5,"porter":null,"nom":"JOAN DANIEL","any":2008,"partits":11,"nom_equip":"Pª BARC. VILLAVERDE-PENITENTS A"},{"codparticipant":30353520,"codequip":38038,"dorsal":8,"titularitats":9,"porter":null,"nom":"ARNAU","any":2008,"partits":11,"nom_equip":"Pª BARC. VILLAVERDE-PENITENTS A"},{"codparticipant":27061166,"codequip":38038,"dorsal":9,"titularitats":9,"porter":null,"nom":"JANUSZ","any":2008,"partits":10,"nom_equip":"Pª BARC. VILLAVERDE-PENITENTS A"},{"codparticipant":30106487,"codequip":38038,"dorsal":11,"titularitats":8,"porter":null,"nom":"JAN","any":2008,"partits":11,"nom_equip":"Pª BARC. VILLAVERDE-PENITENTS A"},{"codparticipant":45424082,"codequip":38038,"dorsal":13,"titularitats":3,"porter":1,"nom":"DIEGO","any":2007,"partits":5,"nom_equip":"Pª BARC. VILLAVERDE-PENITENTS A"},{"codparticipant":33105557,"codequip":38038,"dorsal":15,"titularitats":3,"porter":null,"nom":"NICOLAS","any":2007,"partits":9,"nom_equip":"Pª BARC. VILLAVERDE-PENITENTS A"},{"codparticipant":31976047,"codequip":38038,"dorsal":16,"titularitats":4,"porter":null,"nom":"NIL","any":2007,"partits":11,"nom_equip":"Pª BARC. VILLAVERDE-PENITENTS A"},{"codparticipant":38921689,"codequip":38038,"dorsal":17,"titularitats":8,"porter":null,"nom":"LUCAS","any":2008,"partits":11,"nom_equip":"Pª BARC. VILLAVERDE-PENITENTS A"},{"codparticipant":45401374,"codequip":38038,"dorsal":18,"titularitats":4,"porter":null,"nom":"CARLES","any":2008,"partits":11,"nom_equip":"Pª BARC. VILLAVERDE-PENITENTS A"},{"codparticipant":31044067,"codequip":38038,"dorsal":19,"titularitats":9,"porter":null,"nom":"EDGAR","any":2007,"partits":11,"nom_equip":"Pª BARC. VILLAVERDE-PENITENTS A"},{"codparticipant":45401209,"codequip":38038,"dorsal":20,"titularitats":5,"porter":null,"nom":"HUGO","any":2007,"partits":11,"nom_equip":"Pª BARC. VILLAVERDE-PENITENTS A"},{"codparticipant":33311120,"codequip":38038,"dorsal":22,"titularitats":9,"porter":null,"nom":"WALID","any":2007,"partits":11,"nom_equip":"Pª BARC. VILLAVERDE-PENITENTS A"},{"codparticipant":20131387,"codequip":38038,"dorsal":23,"titularitats":10,"porter":null,"nom":"ALEX","any":2007,"partits":10,"nom_equip":"Pª BARC. VILLAVERDE-PENITENTS A"},{"codparticipant":29817443,"codequip":38038,"dorsal":25,"titularitats":1,"porter":1,"nom":"IZAN","any":2008,"partits":1,"nom_equip":"Pª BARC. VILLAVERDE-PENITENTS A"},{"codparticipant":32612827,"codequip":38038,"dorsal":28,"titularitats":9,"porter":null,"nom":"VICTOR","any":2007,"partits":11,"nom_equip":"Pª BARC. VILLAVERDE-PENITENTS A"},{"codparticipant":45540851,"codequip":38038,"dorsal":30,"titularitats":5,"porter":null,"nom":"ERIC","any":2007,"partits":9,"nom_equip":"Pª BARC. VILLAVERDE-PENITENTS A"},{"codparticipant":29776806,"codequip":38038,"dorsal":37,"titularitats":9,"porter":null,"nom":"BIEL","any":2007,"partits":10,"nom_equip":"Pª BARC. VILLAVERDE-PENITENTS A"}],"codequip":"38038","codgroup":"45060588","menuFollowTeams":[{"label":"Cadet A","href":"/classificacio?id=44766647"},{"label":"Cadet B","href":"/classificacio?id=44766583"},{"label":"Cadet C","href":"/classificacio?id=45060588"},{"label":"Cadet D","href":"/classificacio?id=45061869"}]}