{"data":[{"codgroup":45061869,"codequip":31557692,"nom":"BUFALA, C.F. A","escut":"00100_0000894175_bufalacf_200.png","partits":15,"punts":45,"diff_gols":156,"gols_afavor":159,"gols_encontra":3,"posicio":1},{"codgroup":45061869,"codequip":28495884,"nom":"CONGRÉS CLUB ESP. B","escut":"00100_0000484889_CONGReS_CLUB_ESPORTIU_copia.png","partits":15,"punts":40,"diff_gols":126,"gols_afavor":141,"gols_encontra":15,"posicio":2},{"codgroup":45061869,"codequip":40695586,"nom":"Pª BARC. CINC COPES D","escut":"00100_0000576648_cinccopes_200x200.png","partits":15,"punts":34,"diff_gols":61,"gols_afavor":77,"gols_encontra":16,"posicio":3},{"codgroup":45061869,"codequip":34787994,"nom":"CAN BUXERES, F.C. C","escut":"00100_0000648509_canbuxeres_200x200.png","partits":15,"punts":33,"diff_gols":70,"gols_afavor":91,"gols_encontra":21,"posicio":4},{"codgroup":45061869,"codequip":33454,"nom":"CANYELLES,C.E. A","escut":"00100_0000741560_canyelles_200x200.png","partits":15,"punts":33,"diff_gols":50,"gols_afavor":75,"gols_encontra":25,"posicio":5},{"codgroup":45061869,"codequip":33920,"nom":"MONTAÑESA, C.F. B","escut":"00100_0000584781_montanesa_200x200.png","partits":15,"punts":29,"diff_gols":52,"gols_afavor":77,"gols_encontra":25,"posicio":6},{"codgroup":45061869,"codequip":41030892,"nom":"FUNDACIÓ FUTBOL BADALONA F","escut":"00100_0000599903_ffb_200x200.png","partits":15,"punts":25,"diff_gols":22,"gols_afavor":60,"gols_encontra":38,"posicio":7},{"codgroup":45061869,"codequip":44771497,"nom":"FUNDACIÓ ACADEMIA F. L\\'HOSPITALET  F","escut":"00100_0000817600_faf_200.png","partits":15,"punts":23,"diff_gols":-8,"gols_afavor":37,"gols_encontra":45,"posicio":8},{"codgroup":45061869,"codequip":43974925,"nom":"BALANDRAU, ASSOCIACIÓ CULTURAL  A","escut":"00100_0000881352_balandrau_200.png","partits":15,"punts":22,"diff_gols":-13,"gols_afavor":44,"gols_encontra":57,"posicio":9},{"codgroup":45061869,"codequip":43976449,"nom":"SARRIA, C.P. D","escut":"00100_0000388904_00100_0000337753_escut-cp-sarria-1952.png","partits":15,"punts":20,"diff_gols":-1,"gols_afavor":43,"gols_encontra":44,"posicio":10},{"codgroup":45061869,"codequip":36235866,"nom":"BARCELONETA, C.F. C","escut":"00100_0000173440_LOGO_FCB.png","partits":15,"punts":15,"diff_gols":-65,"gols_afavor":25,"gols_encontra":90,"posicio":11},{"codgroup":45061869,"codequip":18478890,"nom":"TURÓ PEIRA, C.C.D. B","escut":"00100_0000004021_Anagrama 1..png","partits":15,"punts":11,"diff_gols":-42,"gols_afavor":29,"gols_encontra":71,"posicio":12},{"codgroup":45061869,"codequip":40130,"nom":"PENYA BARC. COLLBLANC SANTS,AE B","escut":"00100_0000094725_Escudo3_1.png","partits":15,"punts":10,"diff_gols":-35,"gols_afavor":30,"gols_encontra":65,"posicio":13},{"codgroup":45061869,"codequip":43975215,"nom":"MARTINENC, F.C. F","escut":"00100_0000577607_martinenc-200x200.png","partits":15,"punts":7,"diff_gols":-59,"gols_afavor":22,"gols_encontra":81,"posicio":14},{"codgroup":45061869,"codequip":44606893,"nom":"VALLDOREIX, F.C. C","escut":"00100_0000878137_valldoreixfc_200.png","partits":15,"punts":6,"diff_gols":-63,"gols_afavor":29,"gols_encontra":92,"posicio":15},{"codgroup":45061869,"codequip":34088,"nom":"CARMELO, C.D. B","escut":"00100_0000674925_carmelo_200x200.png","partits":15,"punts":0,"diff_gols":-251,"gols_afavor":6,"gols_encontra":257,"posicio":16}],"dataAcumulada":{"labels":["J1","J2","J3","J4","J5","J6","J7","J8","J9","J10","J11","J12","J13","J14","J15"],"datasets":[{"codequip":41030892,"label":"FUNDACIÓ FUTBOL BADALONA F","data":[3,3,6,9,12,15,15,15,15,15,15,18,19,22,25],"fill":false,"lineTension":0.5,"pointBackgroundColor":"#fff","pointRadius":5,"borderColor":"#8dd3c7","pointBorderColor":"#8dd3c7"},{"codequip":28495884,"label":"CONGRÉS CLUB ESP. B","data":[3,6,9,12,13,16,19,22,25,28,31,34,37,40,40],"fill":false,"lineTension":0.5,"pointBackgroundColor":"#fff","pointRadius":5,"borderColor":"#ffffb3","pointBorderColor":"#ffffb3"},{"codequip":31557692,"label":"BUFALA, C.F. A","data":[3,6,9,12,15,18,21,24,27,30,33,36,39,42,45],"fill":false,"lineTension":0.5,"pointBackgroundColor":"#fff","pointRadius":5,"borderColor":"#bebada","pointBorderColor":"#bebada"},{"codequip":36235866,"label":"BARCELONETA, C.F. C","data":[3,3,3,3,6,9,12,15,15,15,15,15,15,15,15],"fill":false,"lineTension":0.5,"pointBackgroundColor":"#fff","pointRadius":5,"borderColor":"#fb8072","pointBorderColor":"#fb8072"},{"codequip":33920,"label":"MONTAÑESA, C.F. B","data":[3,6,6,9,10,10,10,13,13,16,19,22,23,26,29],"fill":false,"lineTension":0.5,"pointBackgroundColor":"#fff","pointRadius":5,"borderColor":"#80b1d3","pointBorderColor":"#80b1d3"},{"codequip":40695586,"label":"Pª BARC. CINC COPES D","data":[3,6,9,9,12,12,15,16,19,22,25,28,31,31,34],"fill":false,"lineTension":0.5,"pointBackgroundColor":"#fff","pointRadius":5,"borderColor":"#fdb462","pointBorderColor":"#fdb462"},{"codequip":34787994,"label":"CAN BUXERES, F.C. C","data":[3,6,9,12,15,18,18,21,21,24,27,27,27,30,33],"fill":false,"lineTension":0.5,"pointBackgroundColor":"#fff","pointRadius":5,"borderColor":"#b3de69","pointBorderColor":"#b3de69"},{"codequip":43976449,"label":"SARRIA, C.P. D","data":[1,1,1,4,7,7,10,10,11,14,17,17,20,20,20],"fill":false,"lineTension":0.5,"pointBackgroundColor":"#fff","pointRadius":5,"borderColor":"#fccde5","pointBorderColor":"#fccde5"},{"codequip":44771497,"label":"FUNDACIÓ ACADEMIA F. L\\'HOSPITALET  F","data":[1,1,1,1,1,4,7,8,11,14,14,14,17,20,23],"fill":false,"lineTension":0.5,"pointBackgroundColor":"#fff","pointRadius":5,"borderColor":"#d9d9d9","pointBorderColor":"#d9d9d9"},{"codequip":18478890,"label":"TURÓ PEIRA, C.C.D. B","data":[0,0,0,0,0,0,3,3,4,4,4,7,7,10,11],"fill":false,"lineTension":0.5,"pointBackgroundColor":"#fff","pointRadius":5,"borderColor":"#bc80bd","pointBorderColor":"#bc80bd"},{"codequip":40130,"label":"PENYA BARC. COLLBLANC SANTS,AE B","data":[0,3,6,6,6,6,6,9,10,10,10,10,10,10,10],"fill":false,"lineTension":0.5,"pointBackgroundColor":"#fff","pointRadius":5,"borderColor":"#ccebc5","pointBorderColor":"#ccebc5"},{"codequip":43975215,"label":"MARTINENC, F.C. F","data":[0,0,3,6,6,6,6,6,7,7,7,7,7,7,7],"fill":false,"lineTension":0.5,"pointBackgroundColor":"#fff","pointRadius":5,"borderColor":"#ffed6f","pointBorderColor":"#ffed6f"},{"codequip":34088,"label":"CARMELO, C.D. B","data":[0,0,0,0,0,0,0,0,0,0,0,0,0,0,0],"fill":false,"lineTension":0.5,"pointBackgroundColor":"#fff","pointRadius":5,"borderColor":"#8dd3c7","pointBorderColor":"#8dd3c7"},{"codequip":33454,"label":"CANYELLES,C.E. A","data":[0,3,3,6,9,12,12,15,18,18,21,24,27,30,33],"fill":false,"lineTension":0.5,"pointBackgroundColor":"#fff","pointRadius":5,"borderColor":"#ffffb3","pointBorderColor":"#ffffb3"},{"codequip":43974925,"label":"BALANDRAU, ASSOCIACIÓ CULTURAL  A","data":[0,0,3,3,3,6,9,9,12,15,18,21,21,21,22],"fill":false,"lineTension":0.5,"pointBackgroundColor":"#fff","pointRadius":5,"borderColor":"#bebada","pointBorderColor":"#bebada"},{"codequip":44606893,"label":"VALLDOREIX, F.C. C","data":[0,3,3,3,3,3,3,3,3,3,3,3,6,6,6],"fill":false,"lineTension":0.5,"pointBackgroundColor":"#fff","pointRadius":5,"borderColor":"#fb8072","pointBorderColor":"#fb8072"}]},"codgroup":"45061869","menuFollowTeams":[{"label":"Cadet A","href":"/classificacio?id=44766647"},{"label":"Cadet B","href":"/classificacio?id=44766583"},{"label":"Cadet C","href":"/classificacio?id=45060588"},{"label":"Cadet D","href":"/classificacio?id=45061869"}],"maxJornada":30,"jornada":15}