{"data":[{"codparticipant":19897341,"codgroup":44766647,"nom_jugador":"DANER RONALD","any":2007,"codacta":3009703,"codequip":36122,"dorsal":12,"titular":0,"porter":null,"codequip_local":35860,"equip_local":"Pª BARC. ANGUERA B","escut_local":"00100_0000003634_PB ANGUERA.png","colorequipacio1_local":"#FFFF00","codequip_visitant":36122,"equip_visitant":"SANTS, U.E. B","escut_visitant":"00100_0000671592_uesants_200x200.png","colorequipacio1_visitant":"#FFFFFF","jornada":18,"gols_local":4,"gols_visitant":2}],"dataGols":[],"codparticipant":"19897341","codequip":36122,"codgroup":44766647,"menuFollowTeams":[{"label":"Cadet A","href":"/classificacio?id=44766647"},{"label":"Cadet B","href":"/classificacio?id=44766583"},{"label":"Cadet C","href":"/classificacio?id=45060588"},{"label":"Cadet D","href":"/classificacio?id=45061869"}]}