{"data":[{"codparticipant":28529093,"codgroup":44766583,"nom_jugador":"PAU","any":2007,"codacta":3009375,"codequip":36347,"dorsal":12,"titular":1,"porter":null,"codequip_local":36347,"equip_local":"CATALONIA, U.B. A","escut_local":"00100_0000675978_catalonia_200x200.png","colorequipacio1_local":"#FFFFFF","codequip_visitant":41270897,"equip_visitant":"FUNDACIÓ ACADÈMIA F. L\\'HOSPITALET  D","escut_visitant":"00100_0000817600_faf_200.png","colorequipacio1_visitant":"#222222","jornada":7,"gols_local":1,"gols_visitant":2}],"dataGols":[],"codparticipant":"28529093","codequip":36347,"codgroup":44766583,"menuFollowTeams":[{"label":"Cadet A","href":"/classificacio?id=44766647"},{"label":"Cadet B","href":"/classificacio?id=44766583"},{"label":"Cadet C","href":"/classificacio?id=45060588"},{"label":"Cadet D","href":"/classificacio?id=45061869"}]}