{"data":[{"codparticipant":29817443,"codgroup":45060588,"nom_jugador":"IZAN","any":2008,"codacta":3042764,"codequip":38038,"dorsal":25,"titular":1,"porter":1,"codequip_local":38038,"equip_local":"Pª BARC. VILLAVERDE-PENITENTS A","escut_local":"00100_0000012218_Villaverde pequeno.png","colorequipacio1_local":"#FF0000","codequip_visitant":25909655,"equip_visitant":"PENYA BLAUGRANA TRINITAT VELLA A","escut_visitant":"00100_0000162377_ESCUDO_FINAL.png","colorequipacio1_visitant":null,"jornada":7,"gols_local":4,"gols_visitant":0}],"dataGols":[],"codparticipant":"29817443","codequip":38038,"codgroup":45060588,"menuFollowTeams":[{"label":"Cadet A","href":"/classificacio?id=44766647"},{"label":"Cadet B","href":"/classificacio?id=44766583"},{"label":"Cadet C","href":"/classificacio?id=45060588"},{"label":"Cadet D","href":"/classificacio?id=45061869"}]}