{"data":[{"codparticipant":35049497,"nom_jugador":"KIRIAN","dorsal":11,"any":2008,"codequip":41030892,"nom_equip":"FUNDACIÓ FUTBOL BADALONA F","escut":"00100_0000599903_ffb_200x200.png","tipus":"normal","gols":20},{"codparticipant":35015399,"nom_jugador":"FERNANDO","dorsal":7,"any":2007,"codequip":41030892,"nom_equip":"FUNDACIÓ FUTBOL BADALONA F","escut":"00100_0000599903_ffb_200x200.png","tipus":"normal","gols":16},{"codparticipant":26960134,"nom_jugador":"SOULAIMAN","dorsal":11,"any":2008,"codequip":41030892,"nom_equip":"FUNDACIÓ FUTBOL BADALONA F","escut":"00100_0000599903_ffb_200x200.png","tipus":"normal","gols":16},{"codparticipant":18494952,"nom_jugador":"JOSÉ MANUEL","dorsal":6,"any":2007,"codequip":41030892,"nom_equip":"FUNDACIÓ FUTBOL BADALONA F","escut":"00100_0000599903_ffb_200x200.png","tipus":"normal","gols":10},{"codparticipant":45059287,"nom_jugador":"HUGO","dorsal":4,"any":2007,"codequip":41030892,"nom_equip":"FUNDACIÓ FUTBOL BADALONA F","escut":"00100_0000599903_ffb_200x200.png","tipus":"normal","gols":8},{"codparticipant":22465726,"nom_jugador":"CHRISTIAN","dorsal":9,"any":2008,"codequip":41030892,"nom_equip":"FUNDACIÓ FUTBOL BADALONA F","escut":"00100_0000599903_ffb_200x200.png","tipus":"normal","gols":7},{"codparticipant":43483543,"nom_jugador":"ANAS","dorsal":16,"any":2008,"codequip":41030892,"nom_equip":"FUNDACIÓ FUTBOL BADALONA F","escut":"00100_0000599903_ffb_200x200.png","tipus":"normal","gols":4},{"codparticipant":18594690,"nom_jugador":"JOAN","dorsal":8,"any":2007,"codequip":41030892,"nom_equip":"FUNDACIÓ FUTBOL BADALONA F","escut":"00100_0000599903_ffb_200x200.png","tipus":"normal","gols":4},{"codparticipant":38296209,"nom_jugador":"NIKITA","dorsal":14,"any":2007,"codequip":41030892,"nom_equip":"FUNDACIÓ FUTBOL BADALONA F","escut":"00100_0000599903_ffb_200x200.png","tipus":"normal","gols":3},{"codparticipant":35078200,"nom_jugador":"ENZO","dorsal":3,"any":2008,"codequip":41030892,"nom_equip":"FUNDACIÓ FUTBOL BADALONA F","escut":"00100_0000599903_ffb_200x200.png","tipus":"normal","gols":3},{"codparticipant":33374148,"nom_jugador":"ROGER","dorsal":12,"any":2008,"codequip":41030892,"nom_equip":"FUNDACIÓ FUTBOL BADALONA F","escut":"00100_0000599903_ffb_200x200.png","tipus":"normal","gols":3},{"codparticipant":35312328,"nom_jugador":"ALEJANDRO","dorsal":3,"any":2007,"codequip":41030892,"nom_equip":"FUNDACIÓ FUTBOL BADALONA F","escut":"00100_0000599903_ffb_200x200.png","tipus":"normal","gols":1},{"codparticipant":20247431,"nom_jugador":"POL","dorsal":2,"any":2007,"codequip":41030892,"nom_equip":"FUNDACIÓ FUTBOL BADALONA F","escut":"00100_0000599903_ffb_200x200.png","tipus":"normal","gols":1},{"codparticipant":19990647,"nom_jugador":"ALBERT","dorsal":6,"any":2007,"codequip":41030892,"nom_equip":"FUNDACIÓ FUTBOL BADALONA F","escut":"00100_0000599903_ffb_200x200.png","tipus":"normal","gols":1}],"codgroup":"45061869","codequip":"41030892","menuFollowTeams":[{"label":"Cadet A","href":"/classificacio?id=44766647"},{"label":"Cadet B","href":"/classificacio?id=44766583"},{"label":"Cadet C","href":"/classificacio?id=45060588"},{"label":"Cadet D","href":"/classificacio?id=45061869"}]}